[{"actual_issue_date":"1945-08-01T07:00:00.000Z","issue_circulation":1592169,"circulation_quality":"Certified","circulation_source":"ABC","price":"$0.10","publishing_company":"Detective Comics, Inc.","titles_included":"","editor":"","canonical_title":"Batman"},{"actual_issue_date":"1945-10-01T08:00:00.000Z","issue_circulation":1570282,"circulation_quality":"Certified","circulation_source":"ABC","price":"$0.10","publishing_company":"Detective Comics, Inc.","titles_included":"","editor":"","canonical_title":"Batman"},{"actual_issue_date":"1945-12-01T08:00:00.000Z","issue_circulation":1796607,"circulation_quality":"Certified","circulation_source":"ABC","price":"$0.10","publishing_company":"Detective Comics, Inc.","titles_included":"","editor":"","canonical_title":"Batman"},{"actual_issue_date":"1946-02-01T08:00:00.000Z","issue_circulation":1711101,"circulation_quality":"Certified","circulation_source":"ABC","price":"$0.10","publishing_company":"Detective Comics, Inc.","titles_included":"","editor":"","canonical_title":"Batman"},{"actual_issue_date":"1946-04-01T08:00:00.000Z","issue_circulation":1340197,"circulation_quality":"Certified","circulation_source":"ABC","price":"$0.10","publishing_company":"Detective Comics, Inc.","titles_included":"","editor":"","canonical_title":"Batman"},{"actual_issue_date":"1946-06-01T08:00:00.000Z","issue_circulation":1301862,"circulation_quality":"Certified","circulation_source":"ABC","price":"$0.10","publishing_company":"Detective Comics, Inc.","titles_included":"","editor":"","canonical_title":"Batman"},{"actual_issue_date":"1946-08-01T08:00:00.000Z","issue_circulation":1254896,"circulation_quality":"Certified","circulation_source":"ABC","price":"$0.10","publishing_company":"National Comics Publications, Inc.","titles_included":"","editor":"","canonical_title":"Batman"},{"actual_issue_date":"1946-10-01T08:00:00.000Z","issue_circulation":1443972,"circulation_quality":"Certified","circulation_source":"ABC","price":"$0.10","publishing_company":"National Comics Publications, Inc.","titles_included":"","editor":"","canonical_title":"Batman"},{"actual_issue_date":"1946-12-01T08:00:00.000Z","issue_circulation":1346304,"circulation_quality":"Certified","circulation_source":"ABC","price":"$0.10","publishing_company":"National Comics Publications, Inc.","titles_included":"","editor":"","canonical_title":"Batman"},{"actual_issue_date":"1947-02-01T08:00:00.000Z","issue_circulation":1479063,"circulation_quality":"Certified","circulation_source":"ABC","price":"$0.10","publishing_company":"National Comics Publications, Inc.","titles_included":"","editor":"","canonical_title":"Batman"},{"actual_issue_date":"1947-04-01T08:00:00.000Z","issue_circulation":1315605,"circulation_quality":"Certified","circulation_source":"ABC","price":"$0.10","publishing_company":"National Comics Publications, Inc.","titles_included":"","editor":"","canonical_title":"Batman"},{"actual_issue_date":"1947-06-01T08:00:00.000Z","issue_circulation":1198271,"circulation_quality":"Certified","circulation_source":"ABC","price":"$0.10","publishing_company":"National Comics Publications, Inc.","titles_included":"","editor":"","canonical_title":"Batman"}]