[{"sample_period_ending":"1970-12-31T00:00:00Z","sample_period_start":"1970-07-01T00:00:00Z","state_region":"Maine","state_population":992048,"sampled_mail_subscriptions":23,"sampled_single_copy_sales":1353,"sampled_total_sales":1376,"sampled_issue_date":"10/01/1970","magazine_title":"Penthouse","title_code":"PENT"},{"sample_period_ending":"1970-12-31T00:00:00Z","sample_period_start":"1970-07-01T00:00:00Z","state_region":"New Hampshire","state_population":737681,"sampled_mail_subscriptions":41,"sampled_single_copy_sales":1901,"sampled_total_sales":1942,"sampled_issue_date":"10/01/1970","magazine_title":"Penthouse","title_code":"PENT"},{"sample_period_ending":"1970-12-31T00:00:00Z","sample_period_start":"1970-07-01T00:00:00Z","state_region":"Vermont","state_population":444330,"sampled_mail_subscriptions":18,"sampled_single_copy_sales":731,"sampled_total_sales":749,"sampled_issue_date":"10/01/1970","magazine_title":"Penthouse","title_code":"PENT"},{"sample_period_ending":"1970-12-31T00:00:00Z","sample_period_start":"1970-07-01T00:00:00Z","state_region":"Massachusetts","state_population":5689170,"sampled_mail_subscriptions":339,"sampled_single_copy_sales":14406,"sampled_total_sales":14745,"sampled_issue_date":"10/01/1970","magazine_title":"Penthouse","title_code":"PENT"},{"sample_period_ending":"1970-12-31T00:00:00Z","sample_period_start":"1970-07-01T00:00:00Z","state_region":"Rhode Island","state_population":946725,"sampled_mail_subscriptions":51,"sampled_single_copy_sales":1389,"sampled_total_sales":1440,"sampled_issue_date":"10/01/1970","magazine_title":"Penthouse","title_code":"PENT"},{"sample_period_ending":"1970-12-31T00:00:00Z","sample_period_start":"1970-07-01T00:00:00Z","state_region":"Connecticut","state_population":3031709,"sampled_mail_subscriptions":212,"sampled_single_copy_sales":6399,"sampled_total_sales":6611,"sampled_issue_date":"10/01/1970","magazine_title":"Penthouse","title_code":"PENT"},{"sample_period_ending":"1970-12-31T00:00:00Z","sample_period_start":"1970-07-01T00:00:00Z","state_region":"New York","state_population":18236967,"sampled_mail_subscriptions":1389,"sampled_single_copy_sales":43332,"sampled_total_sales":44721,"sampled_issue_date":"10/01/1970","magazine_title":"Penthouse","title_code":"PENT"},{"sample_period_ending":"1970-12-31T00:00:00Z","sample_period_start":"1970-07-01T00:00:00Z","state_region":"New Jersey","state_population":7168164,"sampled_mail_subscriptions":529,"sampled_single_copy_sales":14828,"sampled_total_sales":15357,"sampled_issue_date":"10/01/1970","magazine_title":"Penthouse","title_code":"PENT"},{"sample_period_ending":"1970-12-31T00:00:00Z","sample_period_start":"1970-07-01T00:00:00Z","state_region":"Pennsylvania","state_population":11793909,"sampled_mail_subscriptions":581,"sampled_single_copy_sales":16142,"sampled_total_sales":16723,"sampled_issue_date":"10/01/1970","magazine_title":"Penthouse","title_code":"PENT"},{"sample_period_ending":"1970-12-31T00:00:00Z","sample_period_start":"1970-07-01T00:00:00Z","state_region":"Ohio","state_population":10652017,"sampled_mail_subscriptions":617,"sampled_single_copy_sales":17045,"sampled_total_sales":17662,"sampled_issue_date":"10/01/1970","magazine_title":"Penthouse","title_code":"PENT"},{"sample_period_ending":"1970-12-31T00:00:00Z","sample_period_start":"1970-07-01T00:00:00Z","state_region":"Indiana","state_population":5193669,"sampled_mail_subscriptions":285,"sampled_single_copy_sales":10755,"sampled_total_sales":11040,"sampled_issue_date":"10/01/1970","magazine_title":"Penthouse","title_code":"PENT"},{"sample_period_ending":"1970-12-31T00:00:00Z","sample_period_start":"1970-07-01T00:00:00Z","state_region":"Illinois","state_population":11113976,"sampled_mail_subscriptions":793,"sampled_single_copy_sales":24473,"sampled_total_sales":25266,"sampled_issue_date":"10/01/1970","magazine_title":"Penthouse","title_code":"PENT"},{"sample_period_ending":"1970-12-31T00:00:00Z","sample_period_start":"1970-07-01T00:00:00Z","state_region":"Michigan","state_population":8875083,"sampled_mail_subscriptions":409,"sampled_single_copy_sales":16198,"sampled_total_sales":16607,"sampled_issue_date":"10/01/1970","magazine_title":"Penthouse","title_code":"PENT"},{"sample_period_ending":"1970-12-31T00:00:00Z","sample_period_start":"1970-07-01T00:00:00Z","state_region":"Wisconsin","state_population":4417731,"sampled_mail_subscriptions":271,"sampled_single_copy_sales":7203,"sampled_total_sales":7474,"sampled_issue_date":"10/01/1970","magazine_title":"Penthouse","title_code":"PENT"},{"sample_period_ending":"1970-12-31T00:00:00Z","sample_period_start":"1970-07-01T00:00:00Z","state_region":"Minnesota","state_population":3804971,"sampled_mail_subscriptions":199,"sampled_single_copy_sales":5887,"sampled_total_sales":6086,"sampled_issue_date":"10/01/1970","magazine_title":"Penthouse","title_code":"PENT"},{"sample_period_ending":"1970-12-31T00:00:00Z","sample_period_start":"1970-07-01T00:00:00Z","state_region":"Iowa","state_population":2824376,"sampled_mail_subscriptions":102,"sampled_single_copy_sales":3693,"sampled_total_sales":3795,"sampled_issue_date":"10/01/1970","magazine_title":"Penthouse","title_code":"PENT"},{"sample_period_ending":"1970-12-31T00:00:00Z","sample_period_start":"1970-07-01T00:00:00Z","state_region":"Missouri","state_population":4676501,"sampled_mail_subscriptions":221,"sampled_single_copy_sales":6507,"sampled_total_sales":6728,"sampled_issue_date":"10/01/1970","magazine_title":"Penthouse","title_code":"PENT"},{"sample_period_ending":"1970-12-31T00:00:00Z","sample_period_start":"1970-07-01T00:00:00Z","state_region":"North Dakota","state_population":617761,"sampled_mail_subscriptions":19,"sampled_single_copy_sales":1536,"sampled_total_sales":1555,"sampled_issue_date":"10/01/1970","magazine_title":"Penthouse","title_code":"PENT"},{"sample_period_ending":"1970-12-31T00:00:00Z","sample_period_start":"1970-07-01T00:00:00Z","state_region":"South Dakota","state_population":665507,"sampled_mail_subscriptions":10,"sampled_single_copy_sales":658,"sampled_total_sales":668,"sampled_issue_date":"10/01/1970","magazine_title":"Penthouse","title_code":"PENT"},{"sample_period_ending":"1970-12-31T00:00:00Z","sample_period_start":"1970-07-01T00:00:00Z","state_region":"Nebraska","state_population":1483493,"sampled_mail_subscriptions":60,"sampled_single_copy_sales":1536,"sampled_total_sales":1596,"sampled_issue_date":"10/01/1970","magazine_title":"Penthouse","title_code":"PENT"},{"sample_period_ending":"1970-12-31T00:00:00Z","sample_period_start":"1970-07-01T00:00:00Z","state_region":"Kansas","state_population":2246578,"sampled_mail_subscriptions":94,"sampled_single_copy_sales":3775,"sampled_total_sales":3869,"sampled_issue_date":"10/01/1970","magazine_title":"Penthouse","title_code":"PENT"},{"sample_period_ending":"1970-12-31T00:00:00Z","sample_period_start":"1970-07-01T00:00:00Z","state_region":"Delaware","state_population":548104,"sampled_mail_subscriptions":44,"sampled_single_copy_sales":1170,"sampled_total_sales":1214,"sampled_issue_date":"10/01/1970","magazine_title":"Penthouse","title_code":"PENT"},{"sample_period_ending":"1970-12-31T00:00:00Z","sample_period_start":"1970-07-01T00:00:00Z","state_region":"Maryland","state_population":3922399,"sampled_mail_subscriptions":303,"sampled_single_copy_sales":8454,"sampled_total_sales":8757,"sampled_issue_date":"10/01/1970","magazine_title":"Penthouse","title_code":"PENT"},{"sample_period_ending":"1970-12-31T00:00:00Z","sample_period_start":"1970-07-01T00:00:00Z","state_region":"District of Columbia","state_population":756510,"sampled_mail_subscriptions":52,"sampled_single_copy_sales":6450,"sampled_total_sales":6502,"sampled_issue_date":"10/01/1970","magazine_title":"Penthouse","title_code":"PENT"},{"sample_period_ending":"1970-12-31T00:00:00Z","sample_period_start":"1970-07-01T00:00:00Z","state_region":"Virginia","state_population":4648494,"sampled_mail_subscriptions":260,"sampled_single_copy_sales":8168,"sampled_total_sales":8428,"sampled_issue_date":"10/01/1970","magazine_title":"Penthouse","title_code":"PENT"},{"sample_period_ending":"1970-12-31T00:00:00Z","sample_period_start":"1970-07-01T00:00:00Z","state_region":"West Virginia","state_population":1744237,"sampled_mail_subscriptions":39,"sampled_single_copy_sales":2230,"sampled_total_sales":2269,"sampled_issue_date":"10/01/1970","magazine_title":"Penthouse","title_code":"PENT"},{"sample_period_ending":"1970-12-31T00:00:00Z","sample_period_start":"1970-07-01T00:00:00Z","state_region":"North Carolina","state_population":5082059,"sampled_mail_subscriptions":117,"sampled_single_copy_sales":3730,"sampled_total_sales":3847,"sampled_issue_date":"10/01/1970","magazine_title":"Penthouse","title_code":"PENT"},{"sample_period_ending":"1970-12-31T00:00:00Z","sample_period_start":"1970-07-01T00:00:00Z","state_region":"South Carolina","state_population":2590516,"sampled_mail_subscriptions":94,"sampled_single_copy_sales":2815,"sampled_total_sales":2909,"sampled_issue_date":"10/01/1970","magazine_title":"Penthouse","title_code":"PENT"},{"sample_period_ending":"1970-12-31T00:00:00Z","sample_period_start":"1970-07-01T00:00:00Z","state_region":"Georgia","state_population":4589575,"sampled_mail_subscriptions":218,"sampled_single_copy_sales":13785,"sampled_total_sales":14003,"sampled_issue_date":"10/01/1970","magazine_title":"Penthouse","title_code":"PENT"},{"sample_period_ending":"1970-12-31T00:00:00Z","sample_period_start":"1970-07-01T00:00:00Z","state_region":"Florida","state_population":6789443,"sampled_mail_subscriptions":336,"sampled_single_copy_sales":11847,"sampled_total_sales":12183,"sampled_issue_date":"10/01/1970","magazine_title":"Penthouse","title_code":"PENT"},{"sample_period_ending":"1970-12-31T00:00:00Z","sample_period_start":"1970-07-01T00:00:00Z","state_region":"Kentucky","state_population":3218706,"sampled_mail_subscriptions":111,"sampled_single_copy_sales":4413,"sampled_total_sales":4524,"sampled_issue_date":"10/01/1970","magazine_title":"Penthouse","title_code":"PENT"},{"sample_period_ending":"1970-12-31T00:00:00Z","sample_period_start":"1970-07-01T00:00:00Z","state_region":"Tennessee","state_population":3923687,"sampled_mail_subscriptions":138,"sampled_single_copy_sales":4497,"sampled_total_sales":4635,"sampled_issue_date":"10/01/1970","magazine_title":"Penthouse","title_code":"PENT"},{"sample_period_ending":"1970-12-31T00:00:00Z","sample_period_start":"1970-07-01T00:00:00Z","state_region":"Alabama","state_population":3444165,"sampled_mail_subscriptions":118,"sampled_single_copy_sales":2267,"sampled_total_sales":2385,"sampled_issue_date":"10/01/1970","magazine_title":"Penthouse","title_code":"PENT"},{"sample_period_ending":"1970-12-31T00:00:00Z","sample_period_start":"1970-07-01T00:00:00Z","state_region":"Mississippi","state_population":2216912,"sampled_mail_subscriptions":40,"sampled_single_copy_sales":1133,"sampled_total_sales":1173,"sampled_issue_date":"10/01/1970","magazine_title":"Penthouse","title_code":"PENT"},{"sample_period_ending":"1970-12-31T00:00:00Z","sample_period_start":"1970-07-01T00:00:00Z","state_region":"Arkansas","state_population":1923295,"sampled_mail_subscriptions":35,"sampled_single_copy_sales":1207,"sampled_total_sales":1242,"sampled_issue_date":"10/01/1970","magazine_title":"Penthouse","title_code":"PENT"},{"sample_period_ending":"1970-12-31T00:00:00Z","sample_period_start":"1970-07-01T00:00:00Z","state_region":"Louisiana","state_population":3641306,"sampled_mail_subscriptions":85,"sampled_single_copy_sales":4022,"sampled_total_sales":4107,"sampled_issue_date":"10/01/1970","magazine_title":"Penthouse","title_code":"PENT"},{"sample_period_ending":"1970-12-31T00:00:00Z","sample_period_start":"1970-07-01T00:00:00Z","state_region":"Oklahoma","state_population":2559229,"sampled_mail_subscriptions":80,"sampled_single_copy_sales":4022,"sampled_total_sales":4102,"sampled_issue_date":"10/01/1970","magazine_title":"Penthouse","title_code":"PENT"},{"sample_period_ending":"1970-12-31T00:00:00Z","sample_period_start":"1970-07-01T00:00:00Z","state_region":"Texas","state_population":11196730,"sampled_mail_subscriptions":466,"sampled_single_copy_sales":15101,"sampled_total_sales":15567,"sampled_issue_date":"10/01/1970","magazine_title":"Penthouse","title_code":"PENT"},{"sample_period_ending":"1970-12-31T00:00:00Z","sample_period_start":"1970-07-01T00:00:00Z","state_region":"Montana","state_population":694409,"sampled_mail_subscriptions":8,"sampled_single_copy_sales":1353,"sampled_total_sales":1361,"sampled_issue_date":"10/01/1970","magazine_title":"Penthouse","title_code":"PENT"},{"sample_period_ending":"1970-12-31T00:00:00Z","sample_period_start":"1970-07-01T00:00:00Z","state_region":"Idaho","state_population":712567,"sampled_mail_subscriptions":22,"sampled_single_copy_sales":1389,"sampled_total_sales":1411,"sampled_issue_date":"10/01/1970","magazine_title":"Penthouse","title_code":"PENT"},{"sample_period_ending":"1970-12-31T00:00:00Z","sample_period_start":"1970-07-01T00:00:00Z","state_region":"Wyoming","state_population":332416,"sampled_mail_subscriptions":11,"sampled_single_copy_sales":658,"sampled_total_sales":669,"sampled_issue_date":"10/01/1970","magazine_title":"Penthouse","title_code":"PENT"},{"sample_period_ending":"1970-12-31T00:00:00Z","sample_period_start":"1970-07-01T00:00:00Z","state_region":"Colorado","state_population":2207259,"sampled_mail_subscriptions":101,"sampled_single_copy_sales":6399,"sampled_total_sales":6500,"sampled_issue_date":"10/01/1970","magazine_title":"Penthouse","title_code":"PENT"},{"sample_period_ending":"1970-12-31T00:00:00Z","sample_period_start":"1970-07-01T00:00:00Z","state_region":"New Mexico","state_population":1016000,"sampled_mail_subscriptions":28,"sampled_single_copy_sales":804,"sampled_total_sales":832,"sampled_issue_date":"10/01/1970","magazine_title":"Penthouse","title_code":"PENT"},{"sample_period_ending":"1970-12-31T00:00:00Z","sample_period_start":"1970-07-01T00:00:00Z","state_region":"Arizona","state_population":1770900,"sampled_mail_subscriptions":94,"sampled_single_copy_sales":2614,"sampled_total_sales":2708,"sampled_issue_date":"10/01/1970","magazine_title":"Penthouse","title_code":"PENT"},{"sample_period_ending":"1970-12-31T00:00:00Z","sample_period_start":"1970-07-01T00:00:00Z","state_region":"Utah","state_population":1059273,"sampled_mail_subscriptions":27,"sampled_single_copy_sales":1133,"sampled_total_sales":1160,"sampled_issue_date":"10/01/1970","magazine_title":"Penthouse","title_code":"PENT"},{"sample_period_ending":"1970-12-31T00:00:00Z","sample_period_start":"1970-07-01T00:00:00Z","state_region":"Nevada","state_population":488738,"sampled_mail_subscriptions":22,"sampled_single_copy_sales":2194,"sampled_total_sales":2216,"sampled_issue_date":"10/01/1970","magazine_title":"Penthouse","title_code":"PENT"},{"sample_period_ending":"1970-12-31T00:00:00Z","sample_period_start":"1970-07-01T00:00:00Z","state_region":"Alaska","state_population":300382,"sampled_mail_subscriptions":24,"sampled_single_copy_sales":951,"sampled_total_sales":975,"sampled_issue_date":"10/01/1970","magazine_title":"Penthouse","title_code":"PENT"},{"sample_period_ending":"1970-12-31T00:00:00Z","sample_period_start":"1970-07-01T00:00:00Z","state_region":"Washington","state_population":3409169,"sampled_mail_subscriptions":162,"sampled_single_copy_sales":7532,"sampled_total_sales":7694,"sampled_issue_date":"10/01/1970","magazine_title":"Penthouse","title_code":"PENT"},{"sample_period_ending":"1970-12-31T00:00:00Z","sample_period_start":"1970-07-01T00:00:00Z","state_region":"Oregon","state_population":2091385,"sampled_mail_subscriptions":88,"sampled_single_copy_sales":4644,"sampled_total_sales":4732,"sampled_issue_date":"10/01/1970","magazine_title":"Penthouse","title_code":"PENT"},{"sample_period_ending":"1970-12-31T00:00:00Z","sample_period_start":"1970-07-01T00:00:00Z","state_region":"California","state_population":19953134,"sampled_mail_subscriptions":1002,"sampled_single_copy_sales":41647,"sampled_total_sales":42649,"sampled_issue_date":"10/01/1970","magazine_title":"Penthouse","title_code":"PENT"},{"sample_period_ending":"1970-12-31T00:00:00Z","sample_period_start":"1970-07-01T00:00:00Z","state_region":"Hawaii","state_population":768561,"sampled_mail_subscriptions":48,"sampled_single_copy_sales":1901,"sampled_total_sales":1949,"sampled_issue_date":"10/01/1970","magazine_title":"Penthouse","title_code":"PENT"},{"sample_period_ending":"1970-12-31T00:00:00Z","sample_period_start":"1970-07-01T00:00:00Z","state_region":"Miscellaneous","sampled_mail_subscriptions":0,"sampled_single_copy_sales":0,"sampled_total_sales":0,"sampled_issue_date":"10/01/1970","magazine_title":"Penthouse","title_code":"PENT"},{"sample_period_ending":"1970-12-31T00:00:00Z","sample_period_start":"1970-07-01T00:00:00Z","state_region":"Unclassified","sampled_mail_subscriptions":0,"sampled_single_copy_sales":757,"sampled_total_sales":757,"sampled_issue_date":"10/01/1970","magazine_title":"Penthouse","title_code":"PENT"},{"sample_period_ending":"1970-12-31T00:00:00Z","sample_period_start":"1970-07-01T00:00:00Z","state_region":"Possessions & Other Areas","sampled_mail_subscriptions":0,"sampled_single_copy_sales":1261,"sampled_total_sales":1261,"sampled_issue_date":"10/01/1970","magazine_title":"Penthouse","title_code":"PENT"},{"sample_period_ending":"1970-12-31T00:00:00Z","sample_period_start":"1970-07-01T00:00:00Z","state_region":"U.S. & Possessions, etc.","sampled_mail_subscriptions":10436,"sampled_single_copy_sales":370295,"sampled_total_sales":380731,"sampled_issue_date":"10/01/1970","magazine_title":"Penthouse","title_code":"PENT"},{"sample_period_ending":"1970-12-31T00:00:00Z","sample_period_start":"1970-07-01T00:00:00Z","state_region":"Canada","sampled_mail_subscriptions":216,"sampled_single_copy_sales":21354,"sampled_total_sales":21570,"sampled_issue_date":"10/01/1970","magazine_title":"Penthouse","title_code":"PENT"},{"sample_period_ending":"1970-12-31T00:00:00Z","sample_period_start":"1970-07-01T00:00:00Z","state_region":"Foreign","sampled_mail_subscriptions":14,"sampled_single_copy_sales":0,"sampled_total_sales":14,"sampled_issue_date":"10/01/1970","magazine_title":"Penthouse","title_code":"PENT"},{"sample_period_ending":"1970-12-31T00:00:00Z","sample_period_start":"1970-07-01T00:00:00Z","state_region":"Unclassified","sampled_mail_subscriptions":0,"sampled_single_copy_sales":0,"sampled_total_sales":0,"sampled_issue_date":"10/01/1970","magazine_title":"Penthouse","title_code":"PENT"},{"sample_period_ending":"1970-12-31T00:00:00Z","sample_period_start":"1970-07-01T00:00:00Z","state_region":"Military or Civilian Personnel Overseas","sampled_mail_subscriptions":552,"sampled_single_copy_sales":35541,"sampled_total_sales":36093,"sampled_issue_date":"10/01/1970","magazine_title":"Penthouse","title_code":"PENT"},{"sample_period_ending":"1970-12-31T00:00:00Z","sample_period_start":"1970-07-01T00:00:00Z","state_region":"ALL","sampled_mail_subscriptions":11218,"sampled_single_copy_sales":427190,"sampled_total_sales":438408,"sampled_issue_date":"10/01/1970","magazine_title":"Penthouse","title_code":"PENT"},{"sample_period_ending":"1971-06-30T00:00:00Z","sample_period_start":"1971-01-01T00:00:00Z","state_region":"Maine","state_population":992048,"sampled_mail_subscriptions":15,"sampled_single_copy_sales":2653,"sampled_total_sales":2668,"sampled_issue_date":"05/01/1971","magazine_title":"Penthouse","title_code":"PENT"},{"sample_period_ending":"1971-06-30T00:00:00Z","sample_period_start":"1971-01-01T00:00:00Z","state_region":"New Hampshire","state_population":737681,"sampled_mail_subscriptions":25,"sampled_single_copy_sales":2295,"sampled_total_sales":2320,"sampled_issue_date":"05/01/1971","magazine_title":"Penthouse","title_code":"PENT"},{"sample_period_ending":"1971-06-30T00:00:00Z","sample_period_start":"1971-01-01T00:00:00Z","state_region":"Vermont","state_population":444330,"sampled_mail_subscriptions":8,"sampled_single_copy_sales":1081,"sampled_total_sales":1089,"sampled_issue_date":"05/01/1971","magazine_title":"Penthouse","title_code":"PENT"},{"sample_period_ending":"1971-06-30T00:00:00Z","sample_period_start":"1971-01-01T00:00:00Z","state_region":"Massachusetts","state_population":5689170,"sampled_mail_subscriptions":177,"sampled_single_copy_sales":18974,"sampled_total_sales":19151,"sampled_issue_date":"05/01/1971","magazine_title":"Penthouse","title_code":"PENT"},{"sample_period_ending":"1971-06-30T00:00:00Z","sample_period_start":"1971-01-01T00:00:00Z","state_region":"Rhode Island","state_population":946725,"sampled_mail_subscriptions":33,"sampled_single_copy_sales":3100,"sampled_total_sales":3133,"sampled_issue_date":"05/01/1971","magazine_title":"Penthouse","title_code":"PENT"},{"sample_period_ending":"1971-06-30T00:00:00Z","sample_period_start":"1971-01-01T00:00:00Z","state_region":"Connecticut","state_population":3031709,"sampled_mail_subscriptions":113,"sampled_single_copy_sales":8073,"sampled_total_sales":8186,"sampled_issue_date":"05/01/1971","magazine_title":"Penthouse","title_code":"PENT"},{"sample_period_ending":"1971-06-30T00:00:00Z","sample_period_start":"1971-01-01T00:00:00Z","state_region":"New York","state_population":18236967,"sampled_mail_subscriptions":1029,"sampled_single_copy_sales":59184,"sampled_total_sales":60213,"sampled_issue_date":"05/01/1971","magazine_title":"Penthouse","title_code":"PENT"},{"sample_period_ending":"1971-06-30T00:00:00Z","sample_period_start":"1971-01-01T00:00:00Z","state_region":"New Jersey","state_population":7168164,"sampled_mail_subscriptions":300,"sampled_single_copy_sales":26256,"sampled_total_sales":26556,"sampled_issue_date":"05/01/1971","magazine_title":"Penthouse","title_code":"PENT"},{"sample_period_ending":"1971-06-30T00:00:00Z","sample_period_start":"1971-01-01T00:00:00Z","state_region":"Pennsylvania","state_population":11793909,"sampled_mail_subscriptions":298,"sampled_single_copy_sales":21509,"sampled_total_sales":21807,"sampled_issue_date":"05/01/1971","magazine_title":"Penthouse","title_code":"PENT"},{"sample_period_ending":"1971-06-30T00:00:00Z","sample_period_start":"1971-01-01T00:00:00Z","state_region":"Ohio","state_population":10652017,"sampled_mail_subscriptions":329,"sampled_single_copy_sales":24201,"sampled_total_sales":24530,"sampled_issue_date":"05/01/1971","magazine_title":"Penthouse","title_code":"PENT"},{"sample_period_ending":"1971-06-30T00:00:00Z","sample_period_start":"1971-01-01T00:00:00Z","state_region":"Indiana","state_population":5193669,"sampled_mail_subscriptions":166,"sampled_single_copy_sales":13934,"sampled_total_sales":14100,"sampled_issue_date":"05/01/1971","magazine_title":"Penthouse","title_code":"PENT"},{"sample_period_ending":"1971-06-30T00:00:00Z","sample_period_start":"1971-01-01T00:00:00Z","state_region":"Illinois","state_population":11113976,"sampled_mail_subscriptions":429,"sampled_single_copy_sales":36719,"sampled_total_sales":37148,"sampled_issue_date":"05/01/1971","magazine_title":"Penthouse","title_code":"PENT"},{"sample_period_ending":"1971-06-30T00:00:00Z","sample_period_start":"1971-01-01T00:00:00Z","state_region":"Michigan","state_population":8875083,"sampled_mail_subscriptions":251,"sampled_single_copy_sales":19110,"sampled_total_sales":19361,"sampled_issue_date":"05/01/1971","magazine_title":"Penthouse","title_code":"PENT"},{"sample_period_ending":"1971-06-30T00:00:00Z","sample_period_start":"1971-01-01T00:00:00Z","state_region":"Wisconsin","state_population":4417731,"sampled_mail_subscriptions":124,"sampled_single_copy_sales":13580,"sampled_total_sales":13704,"sampled_issue_date":"05/01/1971","magazine_title":"Penthouse","title_code":"PENT"},{"sample_period_ending":"1971-06-30T00:00:00Z","sample_period_start":"1971-01-01T00:00:00Z","state_region":"Minnesota","state_population":3804971,"sampled_mail_subscriptions":129,"sampled_single_copy_sales":8653,"sampled_total_sales":8782,"sampled_issue_date":"05/01/1971","magazine_title":"Penthouse","title_code":"PENT"},{"sample_period_ending":"1971-06-30T00:00:00Z","sample_period_start":"1971-01-01T00:00:00Z","state_region":"Iowa","state_population":2824376,"sampled_mail_subscriptions":57,"sampled_single_copy_sales":4853,"sampled_total_sales":4910,"sampled_issue_date":"05/01/1971","magazine_title":"Penthouse","title_code":"PENT"},{"sample_period_ending":"1971-06-30T00:00:00Z","sample_period_start":"1971-01-01T00:00:00Z","state_region":"Missouri","state_population":4676501,"sampled_mail_subscriptions":114,"sampled_single_copy_sales":11562,"sampled_total_sales":11676,"sampled_issue_date":"05/01/1971","magazine_title":"Penthouse","title_code":"PENT"},{"sample_period_ending":"1971-06-30T00:00:00Z","sample_period_start":"1971-01-01T00:00:00Z","state_region":"North Dakota","state_population":617761,"sampled_mail_subscriptions":9,"sampled_single_copy_sales":2347,"sampled_total_sales":2356,"sampled_issue_date":"05/01/1971","magazine_title":"Penthouse","title_code":"PENT"},{"sample_period_ending":"1971-06-30T00:00:00Z","sample_period_start":"1971-01-01T00:00:00Z","state_region":"South Dakota","state_population":665507,"sampled_mail_subscriptions":7,"sampled_single_copy_sales":760,"sampled_total_sales":767,"sampled_issue_date":"05/01/1971","magazine_title":"Penthouse","title_code":"PENT"},{"sample_period_ending":"1971-06-30T00:00:00Z","sample_period_start":"1971-01-01T00:00:00Z","state_region":"Nebraska","state_population":1483493,"sampled_mail_subscriptions":52,"sampled_single_copy_sales":3028,"sampled_total_sales":3080,"sampled_issue_date":"05/01/1971","magazine_title":"Penthouse","title_code":"PENT"},{"sample_period_ending":"1971-06-30T00:00:00Z","sample_period_start":"1971-01-01T00:00:00Z","state_region":"Kansas","state_population":2246578,"sampled_mail_subscriptions":97,"sampled_single_copy_sales":5008,"sampled_total_sales":5105,"sampled_issue_date":"05/01/1971","magazine_title":"Penthouse","title_code":"PENT"},{"sample_period_ending":"1971-06-30T00:00:00Z","sample_period_start":"1971-01-01T00:00:00Z","state_region":"Delaware","state_population":548104,"sampled_mail_subscriptions":23,"sampled_single_copy_sales":2878,"sampled_total_sales":2901,"sampled_issue_date":"05/01/1971","magazine_title":"Penthouse","title_code":"PENT"},{"sample_period_ending":"1971-06-30T00:00:00Z","sample_period_start":"1971-01-01T00:00:00Z","state_region":"Maryland","state_population":3922399,"sampled_mail_subscriptions":190,"sampled_single_copy_sales":14318,"sampled_total_sales":14508,"sampled_issue_date":"05/01/1971","magazine_title":"Penthouse","title_code":"PENT"},{"sample_period_ending":"1971-06-30T00:00:00Z","sample_period_start":"1971-01-01T00:00:00Z","state_region":"District of Columbia","state_population":756510,"sampled_mail_subscriptions":35,"sampled_single_copy_sales":8038,"sampled_total_sales":8073,"sampled_issue_date":"05/01/1971","magazine_title":"Penthouse","title_code":"PENT"},{"sample_period_ending":"1971-06-30T00:00:00Z","sample_period_start":"1971-01-01T00:00:00Z","state_region":"Virginia","state_population":4648494,"sampled_mail_subscriptions":171,"sampled_single_copy_sales":15520,"sampled_total_sales":15691,"sampled_issue_date":"05/01/1971","magazine_title":"Penthouse","title_code":"PENT"},{"sample_period_ending":"1971-06-30T00:00:00Z","sample_period_start":"1971-01-01T00:00:00Z","state_region":"West Virginia","state_population":1744237,"sampled_mail_subscriptions":19,"sampled_single_copy_sales":2060,"sampled_total_sales":2079,"sampled_issue_date":"05/01/1971","magazine_title":"Penthouse","title_code":"PENT"},{"sample_period_ending":"1971-06-30T00:00:00Z","sample_period_start":"1971-01-01T00:00:00Z","state_region":"North Carolina","state_population":5082059,"sampled_mail_subscriptions":71,"sampled_single_copy_sales":6542,"sampled_total_sales":6613,"sampled_issue_date":"05/01/1971","magazine_title":"Penthouse","title_code":"PENT"},{"sample_period_ending":"1971-06-30T00:00:00Z","sample_period_start":"1971-01-01T00:00:00Z","state_region":"South Carolina","state_population":2590516,"sampled_mail_subscriptions":59,"sampled_single_copy_sales":4398,"sampled_total_sales":4457,"sampled_issue_date":"05/01/1971","magazine_title":"Penthouse","title_code":"PENT"},{"sample_period_ending":"1971-06-30T00:00:00Z","sample_period_start":"1971-01-01T00:00:00Z","state_region":"Georgia","state_population":4589575,"sampled_mail_subscriptions":147,"sampled_single_copy_sales":19440,"sampled_total_sales":19587,"sampled_issue_date":"05/01/1971","magazine_title":"Penthouse","title_code":"PENT"},{"sample_period_ending":"1971-06-30T00:00:00Z","sample_period_start":"1971-01-01T00:00:00Z","state_region":"Florida","state_population":6789443,"sampled_mail_subscriptions":213,"sampled_single_copy_sales":21056,"sampled_total_sales":21269,"sampled_issue_date":"05/01/1971","magazine_title":"Penthouse","title_code":"PENT"},{"sample_period_ending":"1971-06-30T00:00:00Z","sample_period_start":"1971-01-01T00:00:00Z","state_region":"Kentucky","state_population":3218706,"sampled_mail_subscriptions":64,"sampled_single_copy_sales":8292,"sampled_total_sales":8356,"sampled_issue_date":"05/01/1971","magazine_title":"Penthouse","title_code":"PENT"},{"sample_period_ending":"1971-06-30T00:00:00Z","sample_period_start":"1971-01-01T00:00:00Z","state_region":"Tennessee","state_population":3923687,"sampled_mail_subscriptions":79,"sampled_single_copy_sales":7025,"sampled_total_sales":7104,"sampled_issue_date":"05/01/1971","magazine_title":"Penthouse","title_code":"PENT"},{"sample_period_ending":"1971-06-30T00:00:00Z","sample_period_start":"1971-01-01T00:00:00Z","state_region":"Alabama","state_population":3444165,"sampled_mail_subscriptions":54,"sampled_single_copy_sales":4762,"sampled_total_sales":4816,"sampled_issue_date":"05/01/1971","magazine_title":"Penthouse","title_code":"PENT"},{"sample_period_ending":"1971-06-30T00:00:00Z","sample_period_start":"1971-01-01T00:00:00Z","state_region":"Mississippi","state_population":2216912,"sampled_mail_subscriptions":23,"sampled_single_copy_sales":1709,"sampled_total_sales":1732,"sampled_issue_date":"05/01/1971","magazine_title":"Penthouse","title_code":"PENT"},{"sample_period_ending":"1971-06-30T00:00:00Z","sample_period_start":"1971-01-01T00:00:00Z","state_region":"Arkansas","state_population":1923295,"sampled_mail_subscriptions":25,"sampled_single_copy_sales":2072,"sampled_total_sales":2097,"sampled_issue_date":"05/01/1971","magazine_title":"Penthouse","title_code":"PENT"},{"sample_period_ending":"1971-06-30T00:00:00Z","sample_period_start":"1971-01-01T00:00:00Z","state_region":"Louisiana","state_population":3641306,"sampled_mail_subscriptions":59,"sampled_single_copy_sales":5654,"sampled_total_sales":5713,"sampled_issue_date":"05/01/1971","magazine_title":"Penthouse","title_code":"PENT"},{"sample_period_ending":"1971-06-30T00:00:00Z","sample_period_start":"1971-01-01T00:00:00Z","state_region":"Oklahoma","state_population":2559229,"sampled_mail_subscriptions":61,"sampled_single_copy_sales":7664,"sampled_total_sales":7725,"sampled_issue_date":"05/01/1971","magazine_title":"Penthouse","title_code":"PENT"},{"sample_period_ending":"1971-06-30T00:00:00Z","sample_period_start":"1971-01-01T00:00:00Z","state_region":"Texas","state_population":11196730,"sampled_mail_subscriptions":303,"sampled_single_copy_sales":22711,"sampled_total_sales":23014,"sampled_issue_date":"05/01/1971","magazine_title":"Penthouse","title_code":"PENT"},{"sample_period_ending":"1971-06-30T00:00:00Z","sample_period_start":"1971-01-01T00:00:00Z","state_region":"Montana","state_population":694409,"sampled_mail_subscriptions":9,"sampled_single_copy_sales":1910,"sampled_total_sales":1919,"sampled_issue_date":"05/01/1971","magazine_title":"Penthouse","title_code":"PENT"},{"sample_period_ending":"1971-06-30T00:00:00Z","sample_period_start":"1971-01-01T00:00:00Z","state_region":"Idaho","state_population":712567,"sampled_mail_subscriptions":13,"sampled_single_copy_sales":1737,"sampled_total_sales":1750,"sampled_issue_date":"05/01/1971","magazine_title":"Penthouse","title_code":"PENT"},{"sample_period_ending":"1971-06-30T00:00:00Z","sample_period_start":"1971-01-01T00:00:00Z","state_region":"Wyoming","state_population":332416,"sampled_mail_subscriptions":8,"sampled_single_copy_sales":1228,"sampled_total_sales":1236,"sampled_issue_date":"05/01/1971","magazine_title":"Penthouse","title_code":"PENT"},{"sample_period_ending":"1971-06-30T00:00:00Z","sample_period_start":"1971-01-01T00:00:00Z","state_region":"Colorado","state_population":2207259,"sampled_mail_subscriptions":76,"sampled_single_copy_sales":9913,"sampled_total_sales":9989,"sampled_issue_date":"05/01/1971","magazine_title":"Penthouse","title_code":"PENT"},{"sample_period_ending":"1971-06-30T00:00:00Z","sample_period_start":"1971-01-01T00:00:00Z","state_region":"New Mexico","state_population":1016000,"sampled_mail_subscriptions":30,"sampled_single_copy_sales":1790,"sampled_total_sales":1820,"sampled_issue_date":"05/01/1971","magazine_title":"Penthouse","title_code":"PENT"},{"sample_period_ending":"1971-06-30T00:00:00Z","sample_period_start":"1971-01-01T00:00:00Z","state_region":"Arizona","state_population":1770900,"sampled_mail_subscriptions":68,"sampled_single_copy_sales":3555,"sampled_total_sales":3623,"sampled_issue_date":"05/01/1971","magazine_title":"Penthouse","title_code":"PENT"},{"sample_period_ending":"1971-06-30T00:00:00Z","sample_period_start":"1971-01-01T00:00:00Z","state_region":"Utah","state_population":1059273,"sampled_mail_subscriptions":17,"sampled_single_copy_sales":1686,"sampled_total_sales":1703,"sampled_issue_date":"05/01/1971","magazine_title":"Penthouse","title_code":"PENT"},{"sample_period_ending":"1971-06-30T00:00:00Z","sample_period_start":"1971-01-01T00:00:00Z","state_region":"Nevada","state_population":488738,"sampled_mail_subscriptions":20,"sampled_single_copy_sales":2535,"sampled_total_sales":2555,"sampled_issue_date":"05/01/1971","magazine_title":"Penthouse","title_code":"PENT"},{"sample_period_ending":"1971-06-30T00:00:00Z","sample_period_start":"1971-01-01T00:00:00Z","state_region":"Alaska","state_population":300382,"sampled_mail_subscriptions":20,"sampled_single_copy_sales":2031,"sampled_total_sales":2051,"sampled_issue_date":"05/01/1971","magazine_title":"Penthouse","title_code":"PENT"},{"sample_period_ending":"1971-06-30T00:00:00Z","sample_period_start":"1971-01-01T00:00:00Z","state_region":"Washington","state_population":3409169,"sampled_mail_subscriptions":158,"sampled_single_copy_sales":11585,"sampled_total_sales":11743,"sampled_issue_date":"05/01/1971","magazine_title":"Penthouse","title_code":"PENT"},{"sample_period_ending":"1971-06-30T00:00:00Z","sample_period_start":"1971-01-01T00:00:00Z","state_region":"Oregon","state_population":2091385,"sampled_mail_subscriptions":55,"sampled_single_copy_sales":7425,"sampled_total_sales":7480,"sampled_issue_date":"05/01/1971","magazine_title":"Penthouse","title_code":"PENT"},{"sample_period_ending":"1971-06-30T00:00:00Z","sample_period_start":"1971-01-01T00:00:00Z","state_region":"California","state_population":19953134,"sampled_mail_subscriptions":742,"sampled_single_copy_sales":68371,"sampled_total_sales":69113,"sampled_issue_date":"05/01/1971","magazine_title":"Penthouse","title_code":"PENT"},{"sample_period_ending":"1971-06-30T00:00:00Z","sample_period_start":"1971-01-01T00:00:00Z","state_region":"Hawaii","state_population":768561,"sampled_mail_subscriptions":45,"sampled_single_copy_sales":3708,"sampled_total_sales":3753,"sampled_issue_date":"05/01/1971","magazine_title":"Penthouse","title_code":"PENT"},{"sample_period_ending":"1971-06-30T00:00:00Z","sample_period_start":"1971-01-01T00:00:00Z","state_region":"Miscellaneous","sampled_mail_subscriptions":0,"sampled_single_copy_sales":0,"sampled_total_sales":0,"sampled_issue_date":"05/01/1971","magazine_title":"Penthouse","title_code":"PENT"},{"sample_period_ending":"1971-06-30T00:00:00Z","sample_period_start":"1971-01-01T00:00:00Z","state_region":"Unclassified","sampled_mail_subscriptions":0,"sampled_single_copy_sales":227,"sampled_total_sales":227,"sampled_issue_date":"05/01/1971","magazine_title":"Penthouse","title_code":"PENT"},{"sample_period_ending":"1971-06-30T00:00:00Z","sample_period_start":"1971-01-01T00:00:00Z","state_region":"Possessions & Other Areas","sampled_mail_subscriptions":20,"sampled_single_copy_sales":1589,"sampled_total_sales":1609,"sampled_issue_date":"05/01/1971","magazine_title":"Penthouse","title_code":"PENT"},{"sample_period_ending":"1971-06-30T00:00:00Z","sample_period_start":"1971-01-01T00:00:00Z","state_region":"U.S. & Possessions, etc.","sampled_mail_subscriptions":6639,"sampled_single_copy_sales":560309,"sampled_total_sales":566948,"sampled_issue_date":"05/01/1971","magazine_title":"Penthouse","title_code":"PENT"},{"sample_period_ending":"1971-06-30T00:00:00Z","sample_period_start":"1971-01-01T00:00:00Z","state_region":"Canada","sampled_mail_subscriptions":136,"sampled_single_copy_sales":30728,"sampled_total_sales":30864,"sampled_issue_date":"05/01/1971","magazine_title":"Penthouse","title_code":"PENT"},{"sample_period_ending":"1971-06-30T00:00:00Z","sample_period_start":"1971-01-01T00:00:00Z","state_region":"Foreign","sampled_mail_subscriptions":12,"sampled_single_copy_sales":0,"sampled_total_sales":12,"sampled_issue_date":"05/01/1971","magazine_title":"Penthouse","title_code":"PENT"},{"sample_period_ending":"1971-06-30T00:00:00Z","sample_period_start":"1971-01-01T00:00:00Z","state_region":"Unclassified","sampled_mail_subscriptions":0,"sampled_single_copy_sales":0,"sampled_total_sales":0,"sampled_issue_date":"05/01/1971","magazine_title":"Penthouse","title_code":"PENT"},{"sample_period_ending":"1971-06-30T00:00:00Z","sample_period_start":"1971-01-01T00:00:00Z","state_region":"Military or Civilian Personnel Overseas","sampled_mail_subscriptions":570,"sampled_single_copy_sales":50499,"sampled_total_sales":51069,"sampled_issue_date":"05/01/1971","magazine_title":"Penthouse","title_code":"PENT"},{"sample_period_ending":"1971-06-30T00:00:00Z","sample_period_start":"1971-01-01T00:00:00Z","state_region":"ALL","sampled_mail_subscriptions":7357,"sampled_single_copy_sales":641536,"sampled_total_sales":648893,"sampled_issue_date":"05/01/1971","magazine_title":"Penthouse","title_code":"PENT"},{"sample_period_ending":"1971-12-31T00:00:00Z","sample_period_start":"1971-07-01T00:00:00Z","state_region":"Maine","state_population":992048,"sampled_mail_subscriptions":14,"sampled_single_copy_sales":3850,"sampled_total_sales":3864,"sampled_issue_date":"10/01/1971","magazine_title":"Penthouse","title_code":"PENT"},{"sample_period_ending":"1971-12-31T00:00:00Z","sample_period_start":"1971-07-01T00:00:00Z","state_region":"New Hampshire","state_population":737681,"sampled_mail_subscriptions":31,"sampled_single_copy_sales":3673,"sampled_total_sales":3704,"sampled_issue_date":"10/01/1971","magazine_title":"Penthouse","title_code":"PENT"},{"sample_period_ending":"1971-12-31T00:00:00Z","sample_period_start":"1971-07-01T00:00:00Z","state_region":"Vermont","state_population":444330,"sampled_mail_subscriptions":16,"sampled_single_copy_sales":1307,"sampled_total_sales":1323,"sampled_issue_date":"10/01/1971","magazine_title":"Penthouse","title_code":"PENT"},{"sample_period_ending":"1971-12-31T00:00:00Z","sample_period_start":"1971-07-01T00:00:00Z","state_region":"Massachusetts","state_population":5689170,"sampled_mail_subscriptions":208,"sampled_single_copy_sales":25775,"sampled_total_sales":25983,"sampled_issue_date":"10/01/1971","magazine_title":"Penthouse","title_code":"PENT"},{"sample_period_ending":"1971-12-31T00:00:00Z","sample_period_start":"1971-07-01T00:00:00Z","state_region":"Rhode Island","state_population":946725,"sampled_mail_subscriptions":31,"sampled_single_copy_sales":3285,"sampled_total_sales":3316,"sampled_issue_date":"10/01/1971","magazine_title":"Penthouse","title_code":"PENT"},{"sample_period_ending":"1971-12-31T00:00:00Z","sample_period_start":"1971-07-01T00:00:00Z","state_region":"Connecticut","state_population":3031709,"sampled_mail_subscriptions":122,"sampled_single_copy_sales":10949,"sampled_total_sales":11071,"sampled_issue_date":"10/01/1971","magazine_title":"Penthouse","title_code":"PENT"},{"sample_period_ending":"1971-12-31T00:00:00Z","sample_period_start":"1971-07-01T00:00:00Z","state_region":"New York","state_population":18236967,"sampled_mail_subscriptions":1170,"sampled_single_copy_sales":77704,"sampled_total_sales":78874,"sampled_issue_date":"10/01/1971","magazine_title":"Penthouse","title_code":"PENT"},{"sample_period_ending":"1971-12-31T00:00:00Z","sample_period_start":"1971-07-01T00:00:00Z","state_region":"New Jersey","state_population":7168164,"sampled_mail_subscriptions":333,"sampled_single_copy_sales":32313,"sampled_total_sales":32646,"sampled_issue_date":"10/01/1971","magazine_title":"Penthouse","title_code":"PENT"},{"sample_period_ending":"1971-12-31T00:00:00Z","sample_period_start":"1971-07-01T00:00:00Z","state_region":"Pennsylvania","state_population":11793909,"sampled_mail_subscriptions":351,"sampled_single_copy_sales":35603,"sampled_total_sales":35954,"sampled_issue_date":"10/01/1971","magazine_title":"Penthouse","title_code":"PENT"},{"sample_period_ending":"1971-12-31T00:00:00Z","sample_period_start":"1971-07-01T00:00:00Z","state_region":"Ohio","state_population":10652017,"sampled_mail_subscriptions":363,"sampled_single_copy_sales":43196,"sampled_total_sales":43559,"sampled_issue_date":"10/01/1971","magazine_title":"Penthouse","title_code":"PENT"},{"sample_period_ending":"1971-12-31T00:00:00Z","sample_period_start":"1971-07-01T00:00:00Z","state_region":"Indiana","state_population":5193669,"sampled_mail_subscriptions":187,"sampled_single_copy_sales":19249,"sampled_total_sales":19436,"sampled_issue_date":"10/01/1971","magazine_title":"Penthouse","title_code":"PENT"},{"sample_period_ending":"1971-12-31T00:00:00Z","sample_period_start":"1971-07-01T00:00:00Z","state_region":"Illinois","state_population":11113976,"sampled_mail_subscriptions":471,"sampled_single_copy_sales":59777,"sampled_total_sales":60248,"sampled_issue_date":"10/01/1971","magazine_title":"Penthouse","title_code":"PENT"},{"sample_period_ending":"1971-12-31T00:00:00Z","sample_period_start":"1971-07-01T00:00:00Z","state_region":"Michigan","state_population":8875083,"sampled_mail_subscriptions":264,"sampled_single_copy_sales":30052,"sampled_total_sales":30316,"sampled_issue_date":"10/01/1971","magazine_title":"Penthouse","title_code":"PENT"},{"sample_period_ending":"1971-12-31T00:00:00Z","sample_period_start":"1971-07-01T00:00:00Z","state_region":"Wisconsin","state_population":4417731,"sampled_mail_subscriptions":136,"sampled_single_copy_sales":19068,"sampled_total_sales":19204,"sampled_issue_date":"10/01/1971","magazine_title":"Penthouse","title_code":"PENT"},{"sample_period_ending":"1971-12-31T00:00:00Z","sample_period_start":"1971-07-01T00:00:00Z","state_region":"Minnesota","state_population":3804971,"sampled_mail_subscriptions":127,"sampled_single_copy_sales":10490,"sampled_total_sales":10617,"sampled_issue_date":"10/01/1971","magazine_title":"Penthouse","title_code":"PENT"},{"sample_period_ending":"1971-12-31T00:00:00Z","sample_period_start":"1971-07-01T00:00:00Z","state_region":"Iowa","state_population":2824376,"sampled_mail_subscriptions":71,"sampled_single_copy_sales":5792,"sampled_total_sales":5863,"sampled_issue_date":"10/01/1971","magazine_title":"Penthouse","title_code":"PENT"},{"sample_period_ending":"1971-12-31T00:00:00Z","sample_period_start":"1971-07-01T00:00:00Z","state_region":"Missouri","state_population":4676501,"sampled_mail_subscriptions":153,"sampled_single_copy_sales":16706,"sampled_total_sales":16859,"sampled_issue_date":"10/01/1971","magazine_title":"Penthouse","title_code":"PENT"},{"sample_period_ending":"1971-12-31T00:00:00Z","sample_period_start":"1971-07-01T00:00:00Z","state_region":"North Dakota","state_population":617761,"sampled_mail_subscriptions":11,"sampled_single_copy_sales":5051,"sampled_total_sales":5062,"sampled_issue_date":"10/01/1971","magazine_title":"Penthouse","title_code":"PENT"},{"sample_period_ending":"1971-12-31T00:00:00Z","sample_period_start":"1971-07-01T00:00:00Z","state_region":"South Dakota","state_population":665507,"sampled_mail_subscriptions":9,"sampled_single_copy_sales":1943,"sampled_total_sales":1952,"sampled_issue_date":"10/01/1971","magazine_title":"Penthouse","title_code":"PENT"},{"sample_period_ending":"1971-12-31T00:00:00Z","sample_period_start":"1971-07-01T00:00:00Z","state_region":"Nebraska","state_population":1483493,"sampled_mail_subscriptions":53,"sampled_single_copy_sales":3705,"sampled_total_sales":3758,"sampled_issue_date":"10/01/1971","magazine_title":"Penthouse","title_code":"PENT"},{"sample_period_ending":"1971-12-31T00:00:00Z","sample_period_start":"1971-07-01T00:00:00Z","state_region":"Kansas","state_population":2246578,"sampled_mail_subscriptions":106,"sampled_single_copy_sales":5822,"sampled_total_sales":5928,"sampled_issue_date":"10/01/1971","magazine_title":"Penthouse","title_code":"PENT"},{"sample_period_ending":"1971-12-31T00:00:00Z","sample_period_start":"1971-07-01T00:00:00Z","state_region":"Delaware","state_population":548104,"sampled_mail_subscriptions":22,"sampled_single_copy_sales":4062,"sampled_total_sales":4084,"sampled_issue_date":"10/01/1971","magazine_title":"Penthouse","title_code":"PENT"},{"sample_period_ending":"1971-12-31T00:00:00Z","sample_period_start":"1971-07-01T00:00:00Z","state_region":"Maryland","state_population":3922399,"sampled_mail_subscriptions":191,"sampled_single_copy_sales":14905,"sampled_total_sales":15096,"sampled_issue_date":"10/01/1971","magazine_title":"Penthouse","title_code":"PENT"},{"sample_period_ending":"1971-12-31T00:00:00Z","sample_period_start":"1971-07-01T00:00:00Z","state_region":"District of Columbia","state_population":756510,"sampled_mail_subscriptions":45,"sampled_single_copy_sales":31347,"sampled_total_sales":31392,"sampled_issue_date":"10/01/1971","magazine_title":"Penthouse","title_code":"PENT"},{"sample_period_ending":"1971-12-31T00:00:00Z","sample_period_start":"1971-07-01T00:00:00Z","state_region":"Virginia","state_population":4648494,"sampled_mail_subscriptions":185,"sampled_single_copy_sales":8857,"sampled_total_sales":9042,"sampled_issue_date":"10/01/1971","magazine_title":"Penthouse","title_code":"PENT"},{"sample_period_ending":"1971-12-31T00:00:00Z","sample_period_start":"1971-07-01T00:00:00Z","state_region":"West Virginia","state_population":1744237,"sampled_mail_subscriptions":23,"sampled_single_copy_sales":3178,"sampled_total_sales":3201,"sampled_issue_date":"10/01/1971","magazine_title":"Penthouse","title_code":"PENT"},{"sample_period_ending":"1971-12-31T00:00:00Z","sample_period_start":"1971-07-01T00:00:00Z","state_region":"North Carolina","state_population":5082059,"sampled_mail_subscriptions":77,"sampled_single_copy_sales":11747,"sampled_total_sales":11824,"sampled_issue_date":"10/01/1971","magazine_title":"Penthouse","title_code":"PENT"},{"sample_period_ending":"1971-12-31T00:00:00Z","sample_period_start":"1971-07-01T00:00:00Z","state_region":"South Carolina","state_population":2590516,"sampled_mail_subscriptions":59,"sampled_single_copy_sales":5934,"sampled_total_sales":5993,"sampled_issue_date":"10/01/1971","magazine_title":"Penthouse","title_code":"PENT"},{"sample_period_ending":"1971-12-31T00:00:00Z","sample_period_start":"1971-07-01T00:00:00Z","state_region":"Georgia","state_population":4589575,"sampled_mail_subscriptions":172,"sampled_single_copy_sales":25564,"sampled_total_sales":25736,"sampled_issue_date":"10/01/1971","magazine_title":"Penthouse","title_code":"PENT"},{"sample_period_ending":"1971-12-31T00:00:00Z","sample_period_start":"1971-07-01T00:00:00Z","state_region":"Florida","state_population":6789443,"sampled_mail_subscriptions":247,"sampled_single_copy_sales":34967,"sampled_total_sales":35214,"sampled_issue_date":"10/01/1971","magazine_title":"Penthouse","title_code":"PENT"},{"sample_period_ending":"1971-12-31T00:00:00Z","sample_period_start":"1971-07-01T00:00:00Z","state_region":"Kentucky","state_population":3218706,"sampled_mail_subscriptions":81,"sampled_single_copy_sales":12749,"sampled_total_sales":12830,"sampled_issue_date":"10/01/1971","magazine_title":"Penthouse","title_code":"PENT"},{"sample_period_ending":"1971-12-31T00:00:00Z","sample_period_start":"1971-07-01T00:00:00Z","state_region":"Tennessee","state_population":3923687,"sampled_mail_subscriptions":75,"sampled_single_copy_sales":9848,"sampled_total_sales":9923,"sampled_issue_date":"10/01/1971","magazine_title":"Penthouse","title_code":"PENT"},{"sample_period_ending":"1971-12-31T00:00:00Z","sample_period_start":"1971-07-01T00:00:00Z","state_region":"Alabama","state_population":3444165,"sampled_mail_subscriptions":71,"sampled_single_copy_sales":10349,"sampled_total_sales":10420,"sampled_issue_date":"10/01/1971","magazine_title":"Penthouse","title_code":"PENT"},{"sample_period_ending":"1971-12-31T00:00:00Z","sample_period_start":"1971-07-01T00:00:00Z","state_region":"Mississippi","state_population":2216912,"sampled_mail_subscriptions":29,"sampled_single_copy_sales":3166,"sampled_total_sales":3195,"sampled_issue_date":"10/01/1971","magazine_title":"Penthouse","title_code":"PENT"},{"sample_period_ending":"1971-12-31T00:00:00Z","sample_period_start":"1971-07-01T00:00:00Z","state_region":"Arkansas","state_population":1923295,"sampled_mail_subscriptions":34,"sampled_single_copy_sales":3698,"sampled_total_sales":3732,"sampled_issue_date":"10/01/1971","magazine_title":"Penthouse","title_code":"PENT"},{"sample_period_ending":"1971-12-31T00:00:00Z","sample_period_start":"1971-07-01T00:00:00Z","state_region":"Louisiana","state_population":3641306,"sampled_mail_subscriptions":48,"sampled_single_copy_sales":7543,"sampled_total_sales":7591,"sampled_issue_date":"10/01/1971","magazine_title":"Penthouse","title_code":"PENT"},{"sample_period_ending":"1971-12-31T00:00:00Z","sample_period_start":"1971-07-01T00:00:00Z","state_region":"Oklahoma","state_population":2559229,"sampled_mail_subscriptions":57,"sampled_single_copy_sales":15188,"sampled_total_sales":15245,"sampled_issue_date":"10/01/1971","magazine_title":"Penthouse","title_code":"PENT"},{"sample_period_ending":"1971-12-31T00:00:00Z","sample_period_start":"1971-07-01T00:00:00Z","state_region":"Texas","state_population":11196730,"sampled_mail_subscriptions":329,"sampled_single_copy_sales":40078,"sampled_total_sales":40407,"sampled_issue_date":"10/01/1971","magazine_title":"Penthouse","title_code":"PENT"},{"sample_period_ending":"1971-12-31T00:00:00Z","sample_period_start":"1971-07-01T00:00:00Z","state_region":"Montana","state_population":694409,"sampled_mail_subscriptions":8,"sampled_single_copy_sales":2543,"sampled_total_sales":2551,"sampled_issue_date":"10/01/1971","magazine_title":"Penthouse","title_code":"PENT"},{"sample_period_ending":"1971-12-31T00:00:00Z","sample_period_start":"1971-07-01T00:00:00Z","state_region":"Idaho","state_population":712567,"sampled_mail_subscriptions":14,"sampled_single_copy_sales":2614,"sampled_total_sales":2628,"sampled_issue_date":"10/01/1971","magazine_title":"Penthouse","title_code":"PENT"},{"sample_period_ending":"1971-12-31T00:00:00Z","sample_period_start":"1971-07-01T00:00:00Z","state_region":"Wyoming","state_population":332416,"sampled_mail_subscriptions":7,"sampled_single_copy_sales":1060,"sampled_total_sales":1067,"sampled_issue_date":"10/01/1971","magazine_title":"Penthouse","title_code":"PENT"},{"sample_period_ending":"1971-12-31T00:00:00Z","sample_period_start":"1971-07-01T00:00:00Z","state_region":"Colorado","state_population":2207259,"sampled_mail_subscriptions":90,"sampled_single_copy_sales":15747,"sampled_total_sales":15837,"sampled_issue_date":"10/01/1971","magazine_title":"Penthouse","title_code":"PENT"},{"sample_period_ending":"1971-12-31T00:00:00Z","sample_period_start":"1971-07-01T00:00:00Z","state_region":"New Mexico","state_population":1016000,"sampled_mail_subscriptions":33,"sampled_single_copy_sales":1625,"sampled_total_sales":1658,"sampled_issue_date":"10/01/1971","magazine_title":"Penthouse","title_code":"PENT"},{"sample_period_ending":"1971-12-31T00:00:00Z","sample_period_start":"1971-07-01T00:00:00Z","state_region":"Arizona","state_population":1770900,"sampled_mail_subscriptions":66,"sampled_single_copy_sales":5581,"sampled_total_sales":5647,"sampled_issue_date":"10/01/1971","magazine_title":"Penthouse","title_code":"PENT"},{"sample_period_ending":"1971-12-31T00:00:00Z","sample_period_start":"1971-07-01T00:00:00Z","state_region":"Utah","state_population":1059273,"sampled_mail_subscriptions":26,"sampled_single_copy_sales":2649,"sampled_total_sales":2675,"sampled_issue_date":"10/01/1971","magazine_title":"Penthouse","title_code":"PENT"},{"sample_period_ending":"1971-12-31T00:00:00Z","sample_period_start":"1971-07-01T00:00:00Z","state_region":"Nevada","state_population":488738,"sampled_mail_subscriptions":26,"sampled_single_copy_sales":3603,"sampled_total_sales":3629,"sampled_issue_date":"10/01/1971","magazine_title":"Penthouse","title_code":"PENT"},{"sample_period_ending":"1971-12-31T00:00:00Z","sample_period_start":"1971-07-01T00:00:00Z","state_region":"Alaska","state_population":300382,"sampled_mail_subscriptions":25,"sampled_single_copy_sales":3355,"sampled_total_sales":3380,"sampled_issue_date":"10/01/1971","magazine_title":"Penthouse","title_code":"PENT"},{"sample_period_ending":"1971-12-31T00:00:00Z","sample_period_start":"1971-07-01T00:00:00Z","state_region":"Washington","state_population":3409169,"sampled_mail_subscriptions":182,"sampled_single_copy_sales":18437,"sampled_total_sales":18619,"sampled_issue_date":"10/01/1971","magazine_title":"Penthouse","title_code":"PENT"},{"sample_period_ending":"1971-12-31T00:00:00Z","sample_period_start":"1971-07-01T00:00:00Z","state_region":"Oregon","state_population":2091385,"sampled_mail_subscriptions":66,"sampled_single_copy_sales":10419,"sampled_total_sales":10485,"sampled_issue_date":"10/01/1971","magazine_title":"Penthouse","title_code":"PENT"},{"sample_period_ending":"1971-12-31T00:00:00Z","sample_period_start":"1971-07-01T00:00:00Z","state_region":"California","state_population":19953134,"sampled_mail_subscriptions":804,"sampled_single_copy_sales":97819,"sampled_total_sales":98623,"sampled_issue_date":"10/01/1971","magazine_title":"Penthouse","title_code":"PENT"},{"sample_period_ending":"1971-12-31T00:00:00Z","sample_period_start":"1971-07-01T00:00:00Z","state_region":"Hawaii","state_population":768561,"sampled_mail_subscriptions":48,"sampled_single_copy_sales":1073,"sampled_total_sales":1121,"sampled_issue_date":"10/01/1971","magazine_title":"Penthouse","title_code":"PENT"},{"sample_period_ending":"1971-12-31T00:00:00Z","sample_period_start":"1971-07-01T00:00:00Z","state_region":"Miscellaneous","sampled_mail_subscriptions":0,"sampled_single_copy_sales":0,"sampled_total_sales":0,"sampled_issue_date":"10/01/1971","magazine_title":"Penthouse","title_code":"PENT"},{"sample_period_ending":"1971-12-31T00:00:00Z","sample_period_start":"1971-07-01T00:00:00Z","state_region":"Unclassified","sampled_mail_subscriptions":0,"sampled_single_copy_sales":0,"sampled_total_sales":0,"sampled_issue_date":"10/01/1971","magazine_title":"Penthouse","title_code":"PENT"},{"sample_period_ending":"1971-12-31T00:00:00Z","sample_period_start":"1971-07-01T00:00:00Z","state_region":"Possessions & Other Areas","sampled_mail_subscriptions":18,"sampled_single_copy_sales":1611,"sampled_total_sales":1629,"sampled_issue_date":"10/01/1971","magazine_title":"Penthouse","title_code":"PENT"},{"sample_period_ending":"1971-12-31T00:00:00Z","sample_period_start":"1971-07-01T00:00:00Z","state_region":"U.S. & Possessions, etc.","sampled_mail_subscriptions":7385,"sampled_single_copy_sales":826626,"sampled_total_sales":834011,"sampled_issue_date":"10/01/1971","magazine_title":"Penthouse","title_code":"PENT"},{"sample_period_ending":"1971-12-31T00:00:00Z","sample_period_start":"1971-07-01T00:00:00Z","state_region":"Canada","sampled_mail_subscriptions":193,"sampled_single_copy_sales":50331,"sampled_total_sales":50524,"sampled_issue_date":"10/01/1971","magazine_title":"Penthouse","title_code":"PENT"},{"sample_period_ending":"1971-12-31T00:00:00Z","sample_period_start":"1971-07-01T00:00:00Z","state_region":"Foreign","sampled_mail_subscriptions":5,"sampled_single_copy_sales":0,"sampled_total_sales":5,"sampled_issue_date":"10/01/1971","magazine_title":"Penthouse","title_code":"PENT"},{"sample_period_ending":"1971-12-31T00:00:00Z","sample_period_start":"1971-07-01T00:00:00Z","state_region":"Unclassified","sampled_mail_subscriptions":0,"sampled_single_copy_sales":0,"sampled_total_sales":0,"sampled_issue_date":"10/01/1971","magazine_title":"Penthouse","title_code":"PENT"},{"sample_period_ending":"1971-12-31T00:00:00Z","sample_period_start":"1971-07-01T00:00:00Z","state_region":"Military or Civilian Personnel Overseas","sampled_mail_subscriptions":500,"sampled_single_copy_sales":52543,"sampled_total_sales":53043,"sampled_issue_date":"10/01/1971","magazine_title":"Penthouse","title_code":"PENT"},{"sample_period_ending":"1971-12-31T00:00:00Z","sample_period_start":"1971-07-01T00:00:00Z","state_region":"ALL","sampled_mail_subscriptions":8083,"sampled_single_copy_sales":929500,"sampled_total_sales":937583,"sampled_issue_date":"10/01/1971","magazine_title":"Penthouse","title_code":"PENT"},{"sample_period_ending":"1972-06-30T00:00:00Z","sample_period_start":"1972-01-01T00:00:00Z","state_region":"Maine","state_population":992048,"sampled_mail_subscriptions":56,"sampled_single_copy_sales":6689,"sampled_total_sales":6745,"sampled_issue_date":"05/01/1972","magazine_title":"Penthouse","title_code":"PENT"},{"sample_period_ending":"1972-06-30T00:00:00Z","sample_period_start":"1972-01-01T00:00:00Z","state_region":"New Hampshire","state_population":737681,"sampled_mail_subscriptions":75,"sampled_single_copy_sales":5792,"sampled_total_sales":5867,"sampled_issue_date":"05/01/1972","magazine_title":"Penthouse","title_code":"PENT"},{"sample_period_ending":"1972-06-30T00:00:00Z","sample_period_start":"1972-01-01T00:00:00Z","state_region":"Vermont","state_population":444330,"sampled_mail_subscriptions":37,"sampled_single_copy_sales":1782,"sampled_total_sales":1819,"sampled_issue_date":"05/01/1972","magazine_title":"Penthouse","title_code":"PENT"},{"sample_period_ending":"1972-06-30T00:00:00Z","sample_period_start":"1972-01-01T00:00:00Z","state_region":"Massachusetts","state_population":5689170,"sampled_mail_subscriptions":590,"sampled_single_copy_sales":45495,"sampled_total_sales":46085,"sampled_issue_date":"05/01/1972","magazine_title":"Penthouse","title_code":"PENT"},{"sample_period_ending":"1972-06-30T00:00:00Z","sample_period_start":"1972-01-01T00:00:00Z","state_region":"Rhode Island","state_population":946725,"sampled_mail_subscriptions":107,"sampled_single_copy_sales":3960,"sampled_total_sales":4067,"sampled_issue_date":"05/01/1972","magazine_title":"Penthouse","title_code":"PENT"},{"sample_period_ending":"1972-06-30T00:00:00Z","sample_period_start":"1972-01-01T00:00:00Z","state_region":"Connecticut","state_population":3031709,"sampled_mail_subscriptions":301,"sampled_single_copy_sales":16566,"sampled_total_sales":16867,"sampled_issue_date":"05/01/1972","magazine_title":"Penthouse","title_code":"PENT"},{"sample_period_ending":"1972-06-30T00:00:00Z","sample_period_start":"1972-01-01T00:00:00Z","state_region":"New York","state_population":18236967,"sampled_mail_subscriptions":2364,"sampled_single_copy_sales":142146,"sampled_total_sales":144510,"sampled_issue_date":"05/01/1972","magazine_title":"Penthouse","title_code":"PENT"},{"sample_period_ending":"1972-06-30T00:00:00Z","sample_period_start":"1972-01-01T00:00:00Z","state_region":"New Jersey","state_population":7168164,"sampled_mail_subscriptions":798,"sampled_single_copy_sales":48378,"sampled_total_sales":49176,"sampled_issue_date":"05/01/1972","magazine_title":"Penthouse","title_code":"PENT"},{"sample_period_ending":"1972-06-30T00:00:00Z","sample_period_start":"1972-01-01T00:00:00Z","state_region":"Pennsylvania","state_population":11793909,"sampled_mail_subscriptions":1059,"sampled_single_copy_sales":66165,"sampled_total_sales":67224,"sampled_issue_date":"05/01/1972","magazine_title":"Penthouse","title_code":"PENT"},{"sample_period_ending":"1972-06-30T00:00:00Z","sample_period_start":"1972-01-01T00:00:00Z","state_region":"Ohio","state_population":10652017,"sampled_mail_subscriptions":1066,"sampled_single_copy_sales":72699,"sampled_total_sales":73765,"sampled_issue_date":"05/01/1972","magazine_title":"Penthouse","title_code":"PENT"},{"sample_period_ending":"1972-06-30T00:00:00Z","sample_period_start":"1972-01-01T00:00:00Z","state_region":"Indiana","state_population":5193669,"sampled_mail_subscriptions":528,"sampled_single_copy_sales":33000,"sampled_total_sales":33528,"sampled_issue_date":"05/01/1972","magazine_title":"Penthouse","title_code":"PENT"},{"sample_period_ending":"1972-06-30T00:00:00Z","sample_period_start":"1972-01-01T00:00:00Z","state_region":"Illinois","state_population":11113976,"sampled_mail_subscriptions":1160,"sampled_single_copy_sales":78926,"sampled_total_sales":80086,"sampled_issue_date":"05/01/1972","magazine_title":"Penthouse","title_code":"PENT"},{"sample_period_ending":"1972-06-30T00:00:00Z","sample_period_start":"1972-01-01T00:00:00Z","state_region":"Michigan","state_population":8875083,"sampled_mail_subscriptions":751,"sampled_single_copy_sales":50116,"sampled_total_sales":50867,"sampled_issue_date":"05/01/1972","magazine_title":"Penthouse","title_code":"PENT"},{"sample_period_ending":"1972-06-30T00:00:00Z","sample_period_start":"1972-01-01T00:00:00Z","state_region":"Wisconsin","state_population":4417731,"sampled_mail_subscriptions":470,"sampled_single_copy_sales":28198,"sampled_total_sales":28668,"sampled_issue_date":"05/01/1972","magazine_title":"Penthouse","title_code":"PENT"},{"sample_period_ending":"1972-06-30T00:00:00Z","sample_period_start":"1972-01-01T00:00:00Z","state_region":"Minnesota","state_population":3804971,"sampled_mail_subscriptions":243,"sampled_single_copy_sales":26334,"sampled_total_sales":26577,"sampled_issue_date":"05/01/1972","magazine_title":"Penthouse","title_code":"PENT"},{"sample_period_ending":"1972-06-30T00:00:00Z","sample_period_start":"1972-01-01T00:00:00Z","state_region":"Iowa","state_population":2824376,"sampled_mail_subscriptions":178,"sampled_single_copy_sales":11583,"sampled_total_sales":11761,"sampled_issue_date":"05/01/1972","magazine_title":"Penthouse","title_code":"PENT"},{"sample_period_ending":"1972-06-30T00:00:00Z","sample_period_start":"1972-01-01T00:00:00Z","state_region":"Missouri","state_population":4676501,"sampled_mail_subscriptions":440,"sampled_single_copy_sales":32670,"sampled_total_sales":33110,"sampled_issue_date":"05/01/1972","magazine_title":"Penthouse","title_code":"PENT"},{"sample_period_ending":"1972-06-30T00:00:00Z","sample_period_start":"1972-01-01T00:00:00Z","state_region":"North Dakota","state_population":617761,"sampled_mail_subscriptions":40,"sampled_single_copy_sales":3927,"sampled_total_sales":3967,"sampled_issue_date":"05/01/1972","magazine_title":"Penthouse","title_code":"PENT"},{"sample_period_ending":"1972-06-30T00:00:00Z","sample_period_start":"1972-01-01T00:00:00Z","state_region":"South Dakota","state_population":665507,"sampled_mail_subscriptions":24,"sampled_single_copy_sales":3267,"sampled_total_sales":3291,"sampled_issue_date":"05/01/1972","magazine_title":"Penthouse","title_code":"PENT"},{"sample_period_ending":"1972-06-30T00:00:00Z","sample_period_start":"1972-01-01T00:00:00Z","state_region":"Nebraska","state_population":1483493,"sampled_mail_subscriptions":156,"sampled_single_copy_sales":9306,"sampled_total_sales":9462,"sampled_issue_date":"05/01/1972","magazine_title":"Penthouse","title_code":"PENT"},{"sample_period_ending":"1972-06-30T00:00:00Z","sample_period_start":"1972-01-01T00:00:00Z","state_region":"Kansas","state_population":2246578,"sampled_mail_subscriptions":288,"sampled_single_copy_sales":13447,"sampled_total_sales":13735,"sampled_issue_date":"05/01/1972","magazine_title":"Penthouse","title_code":"PENT"},{"sample_period_ending":"1972-06-30T00:00:00Z","sample_period_start":"1972-01-01T00:00:00Z","state_region":"Delaware","state_population":548104,"sampled_mail_subscriptions":66,"sampled_single_copy_sales":9900,"sampled_total_sales":9966,"sampled_issue_date":"05/01/1972","magazine_title":"Penthouse","title_code":"PENT"},{"sample_period_ending":"1972-06-30T00:00:00Z","sample_period_start":"1972-01-01T00:00:00Z","state_region":"Maryland","state_population":3922399,"sampled_mail_subscriptions":573,"sampled_single_copy_sales":38996,"sampled_total_sales":39569,"sampled_issue_date":"05/01/1972","magazine_title":"Penthouse","title_code":"PENT"},{"sample_period_ending":"1972-06-30T00:00:00Z","sample_period_start":"1972-01-01T00:00:00Z","state_region":"District of Columbia","state_population":756510,"sampled_mail_subscriptions":164,"sampled_single_copy_sales":23419,"sampled_total_sales":23583,"sampled_issue_date":"05/01/1972","magazine_title":"Penthouse","title_code":"PENT"},{"sample_period_ending":"1972-06-30T00:00:00Z","sample_period_start":"1972-01-01T00:00:00Z","state_region":"Virginia","state_population":4648494,"sampled_mail_subscriptions":581,"sampled_single_copy_sales":28988,"sampled_total_sales":29569,"sampled_issue_date":"05/01/1972","magazine_title":"Penthouse","title_code":"PENT"},{"sample_period_ending":"1972-06-30T00:00:00Z","sample_period_start":"1972-01-01T00:00:00Z","state_region":"West Virginia","state_population":1744237,"sampled_mail_subscriptions":87,"sampled_single_copy_sales":5344,"sampled_total_sales":5431,"sampled_issue_date":"05/01/1972","magazine_title":"Penthouse","title_code":"PENT"},{"sample_period_ending":"1972-06-30T00:00:00Z","sample_period_start":"1972-01-01T00:00:00Z","state_region":"North Carolina","state_population":5082059,"sampled_mail_subscriptions":383,"sampled_single_copy_sales":26829,"sampled_total_sales":27212,"sampled_issue_date":"05/01/1972","magazine_title":"Penthouse","title_code":"PENT"},{"sample_period_ending":"1972-06-30T00:00:00Z","sample_period_start":"1972-01-01T00:00:00Z","state_region":"South Carolina","state_population":2590516,"sampled_mail_subscriptions":281,"sampled_single_copy_sales":10164,"sampled_total_sales":10445,"sampled_issue_date":"05/01/1972","magazine_title":"Penthouse","title_code":"PENT"},{"sample_period_ending":"1972-06-30T00:00:00Z","sample_period_start":"1972-01-01T00:00:00Z","state_region":"Georgia","state_population":4589575,"sampled_mail_subscriptions":512,"sampled_single_copy_sales":44121,"sampled_total_sales":44633,"sampled_issue_date":"05/01/1972","magazine_title":"Penthouse","title_code":"PENT"},{"sample_period_ending":"1972-06-30T00:00:00Z","sample_period_start":"1972-01-01T00:00:00Z","state_region":"Florida","state_population":6789443,"sampled_mail_subscriptions":859,"sampled_single_copy_sales":70092,"sampled_total_sales":70951,"sampled_issue_date":"05/01/1972","magazine_title":"Penthouse","title_code":"PENT"},{"sample_period_ending":"1972-06-30T00:00:00Z","sample_period_start":"1972-01-01T00:00:00Z","state_region":"Kentucky","state_population":3218706,"sampled_mail_subscriptions":257,"sampled_single_copy_sales":13693,"sampled_total_sales":13950,"sampled_issue_date":"05/01/1972","magazine_title":"Penthouse","title_code":"PENT"},{"sample_period_ending":"1972-06-30T00:00:00Z","sample_period_start":"1972-01-01T00:00:00Z","state_region":"Tennessee","state_population":3923687,"sampled_mail_subscriptions":224,"sampled_single_copy_sales":20460,"sampled_total_sales":20684,"sampled_issue_date":"05/01/1972","magazine_title":"Penthouse","title_code":"PENT"},{"sample_period_ending":"1972-06-30T00:00:00Z","sample_period_start":"1972-01-01T00:00:00Z","state_region":"Alabama","state_population":3444165,"sampled_mail_subscriptions":223,"sampled_single_copy_sales":18545,"sampled_total_sales":18768,"sampled_issue_date":"05/01/1972","magazine_title":"Penthouse","title_code":"PENT"},{"sample_period_ending":"1972-06-30T00:00:00Z","sample_period_start":"1972-01-01T00:00:00Z","state_region":"Mississippi","state_population":2216912,"sampled_mail_subscriptions":85,"sampled_single_copy_sales":7557,"sampled_total_sales":7642,"sampled_issue_date":"05/01/1972","magazine_title":"Penthouse","title_code":"PENT"},{"sample_period_ending":"1972-06-30T00:00:00Z","sample_period_start":"1972-01-01T00:00:00Z","state_region":"Arkansas","state_population":1923295,"sampled_mail_subscriptions":129,"sampled_single_copy_sales":6850,"sampled_total_sales":6979,"sampled_issue_date":"05/01/1972","magazine_title":"Penthouse","title_code":"PENT"},{"sample_period_ending":"1972-06-30T00:00:00Z","sample_period_start":"1972-01-01T00:00:00Z","state_region":"Louisiana","state_population":3641306,"sampled_mail_subscriptions":210,"sampled_single_copy_sales":14119,"sampled_total_sales":14329,"sampled_issue_date":"05/01/1972","magazine_title":"Penthouse","title_code":"PENT"},{"sample_period_ending":"1972-06-30T00:00:00Z","sample_period_start":"1972-01-01T00:00:00Z","state_region":"Oklahoma","state_population":2559229,"sampled_mail_subscriptions":114,"sampled_single_copy_sales":34551,"sampled_total_sales":34665,"sampled_issue_date":"05/01/1972","magazine_title":"Penthouse","title_code":"PENT"},{"sample_period_ending":"1972-06-30T00:00:00Z","sample_period_start":"1972-01-01T00:00:00Z","state_region":"Texas","state_population":11196730,"sampled_mail_subscriptions":939,"sampled_single_copy_sales":72719,"sampled_total_sales":73658,"sampled_issue_date":"05/01/1972","magazine_title":"Penthouse","title_code":"PENT"},{"sample_period_ending":"1972-06-30T00:00:00Z","sample_period_start":"1972-01-01T00:00:00Z","state_region":"Montana","state_population":694409,"sampled_mail_subscriptions":41,"sampled_single_copy_sales":4283,"sampled_total_sales":4324,"sampled_issue_date":"05/01/1972","magazine_title":"Penthouse","title_code":"PENT"},{"sample_period_ending":"1972-06-30T00:00:00Z","sample_period_start":"1972-01-01T00:00:00Z","state_region":"Idaho","state_population":712567,"sampled_mail_subscriptions":42,"sampled_single_copy_sales":4587,"sampled_total_sales":4629,"sampled_issue_date":"05/01/1972","magazine_title":"Penthouse","title_code":"PENT"},{"sample_period_ending":"1972-06-30T00:00:00Z","sample_period_start":"1972-01-01T00:00:00Z","state_region":"Wyoming","state_population":332416,"sampled_mail_subscriptions":25,"sampled_single_copy_sales":1650,"sampled_total_sales":1675,"sampled_issue_date":"05/01/1972","magazine_title":"Penthouse","title_code":"PENT"},{"sample_period_ending":"1972-06-30T00:00:00Z","sample_period_start":"1972-01-01T00:00:00Z","state_region":"Colorado","state_population":2207259,"sampled_mail_subscriptions":263,"sampled_single_copy_sales":29460,"sampled_total_sales":29723,"sampled_issue_date":"05/01/1972","magazine_title":"Penthouse","title_code":"PENT"},{"sample_period_ending":"1972-06-30T00:00:00Z","sample_period_start":"1972-01-01T00:00:00Z","state_region":"New Mexico","state_population":1016000,"sampled_mail_subscriptions":75,"sampled_single_copy_sales":3267,"sampled_total_sales":3342,"sampled_issue_date":"05/01/1972","magazine_title":"Penthouse","title_code":"PENT"},{"sample_period_ending":"1972-06-30T00:00:00Z","sample_period_start":"1972-01-01T00:00:00Z","state_region":"Arizona","state_population":1770900,"sampled_mail_subscriptions":167,"sampled_single_copy_sales":10989,"sampled_total_sales":11156,"sampled_issue_date":"05/01/1972","magazine_title":"Penthouse","title_code":"PENT"},{"sample_period_ending":"1972-06-30T00:00:00Z","sample_period_start":"1972-01-01T00:00:00Z","state_region":"Utah","state_population":1059273,"sampled_mail_subscriptions":64,"sampled_single_copy_sales":6421,"sampled_total_sales":6485,"sampled_issue_date":"05/01/1972","magazine_title":"Penthouse","title_code":"PENT"},{"sample_period_ending":"1972-06-30T00:00:00Z","sample_period_start":"1972-01-01T00:00:00Z","state_region":"Nevada","state_population":488738,"sampled_mail_subscriptions":65,"sampled_single_copy_sales":8019,"sampled_total_sales":8084,"sampled_issue_date":"05/01/1972","magazine_title":"Penthouse","title_code":"PENT"},{"sample_period_ending":"1972-06-30T00:00:00Z","sample_period_start":"1972-01-01T00:00:00Z","state_region":"Alaska","state_population":300382,"sampled_mail_subscriptions":60,"sampled_single_copy_sales":4125,"sampled_total_sales":4185,"sampled_issue_date":"05/01/1972","magazine_title":"Penthouse","title_code":"PENT"},{"sample_period_ending":"1972-06-30T00:00:00Z","sample_period_start":"1972-01-01T00:00:00Z","state_region":"Washington","state_population":3409169,"sampled_mail_subscriptions":381,"sampled_single_copy_sales":24571,"sampled_total_sales":24952,"sampled_issue_date":"05/01/1972","magazine_title":"Penthouse","title_code":"PENT"},{"sample_period_ending":"1972-06-30T00:00:00Z","sample_period_start":"1972-01-01T00:00:00Z","state_region":"Oregon","state_population":2091385,"sampled_mail_subscriptions":173,"sampled_single_copy_sales":14388,"sampled_total_sales":14561,"sampled_issue_date":"05/01/1972","magazine_title":"Penthouse","title_code":"PENT"},{"sample_period_ending":"1972-06-30T00:00:00Z","sample_period_start":"1972-01-01T00:00:00Z","state_region":"California","state_population":19953134,"sampled_mail_subscriptions":2248,"sampled_single_copy_sales":214890,"sampled_total_sales":217138,"sampled_issue_date":"05/01/1972","magazine_title":"Penthouse","title_code":"PENT"},{"sample_period_ending":"1972-06-30T00:00:00Z","sample_period_start":"1972-01-01T00:00:00Z","state_region":"Hawaii","state_population":768561,"sampled_mail_subscriptions":83,"sampled_single_copy_sales":5775,"sampled_total_sales":5858,"sampled_issue_date":"05/01/1972","magazine_title":"Penthouse","title_code":"PENT"},{"sample_period_ending":"1972-06-30T00:00:00Z","sample_period_start":"1972-01-01T00:00:00Z","state_region":"Miscellaneous","sampled_mail_subscriptions":0,"sampled_single_copy_sales":0,"sampled_total_sales":0,"sampled_issue_date":"05/01/1972","magazine_title":"Penthouse","title_code":"PENT"},{"sample_period_ending":"1972-06-30T00:00:00Z","sample_period_start":"1972-01-01T00:00:00Z","state_region":"Unclassified","sampled_mail_subscriptions":0,"sampled_single_copy_sales":0,"sampled_total_sales":0,"sampled_issue_date":"05/01/1972","magazine_title":"Penthouse","title_code":"PENT"},{"sample_period_ending":"1972-06-30T00:00:00Z","sample_period_start":"1972-01-01T00:00:00Z","state_region":"Possessions & Other Areas","sampled_mail_subscriptions":24,"sampled_single_copy_sales":1959,"sampled_total_sales":1983,"sampled_issue_date":"05/01/1972","magazine_title":"Penthouse","title_code":"PENT"},{"sample_period_ending":"1972-06-30T00:00:00Z","sample_period_start":"1972-01-01T00:00:00Z","state_region":"U.S. & Possessions, etc.","sampled_mail_subscriptions":20129,"sampled_single_copy_sales":1481177,"sampled_total_sales":1501306,"sampled_issue_date":"05/01/1972","magazine_title":"Penthouse","title_code":"PENT"},{"sample_period_ending":"1972-06-30T00:00:00Z","sample_period_start":"1972-01-01T00:00:00Z","state_region":"Canada","sampled_mail_subscriptions":591,"sampled_single_copy_sales":107217,"sampled_total_sales":107808,"sampled_issue_date":"05/01/1972","magazine_title":"Penthouse","title_code":"PENT"},{"sample_period_ending":"1972-06-30T00:00:00Z","sample_period_start":"1972-01-01T00:00:00Z","state_region":"Foreign","sampled_mail_subscriptions":41,"sampled_single_copy_sales":0,"sampled_total_sales":41,"sampled_issue_date":"05/01/1972","magazine_title":"Penthouse","title_code":"PENT"},{"sample_period_ending":"1972-06-30T00:00:00Z","sample_period_start":"1972-01-01T00:00:00Z","state_region":"Unclassified","sampled_mail_subscriptions":0,"sampled_single_copy_sales":0,"sampled_total_sales":0,"sampled_issue_date":"05/01/1972","magazine_title":"Penthouse","title_code":"PENT"},{"sample_period_ending":"1972-06-30T00:00:00Z","sample_period_start":"1972-01-01T00:00:00Z","state_region":"Military or Civilian Personnel Overseas","sampled_mail_subscriptions":1057,"sampled_single_copy_sales":56080,"sampled_total_sales":57137,"sampled_issue_date":"05/01/1972","magazine_title":"Penthouse","title_code":"PENT"},{"sample_period_ending":"1972-06-30T00:00:00Z","sample_period_start":"1972-01-01T00:00:00Z","state_region":"ALL","sampled_mail_subscriptions":21818,"sampled_single_copy_sales":1644474,"sampled_total_sales":1666292,"sampled_issue_date":"05/01/1972","magazine_title":"Penthouse","title_code":"PENT"},{"sample_period_ending":"1972-12-31T00:00:00Z","sample_period_start":"1972-07-01T00:00:00Z","state_region":"Maine","state_population":992048,"sampled_mail_subscriptions":127,"sampled_single_copy_sales":9490,"sampled_total_sales":9617,"sampled_issue_date":"11/01/1972","magazine_title":"Penthouse","title_code":"PENT"},{"sample_period_ending":"1972-12-31T00:00:00Z","sample_period_start":"1972-07-01T00:00:00Z","state_region":"New Hampshire","state_population":737681,"sampled_mail_subscriptions":120,"sampled_single_copy_sales":10140,"sampled_total_sales":10260,"sampled_issue_date":"11/01/1972","magazine_title":"Penthouse","title_code":"PENT"},{"sample_period_ending":"1972-12-31T00:00:00Z","sample_period_start":"1972-07-01T00:00:00Z","state_region":"Vermont","state_population":444330,"sampled_mail_subscriptions":70,"sampled_single_copy_sales":4680,"sampled_total_sales":4750,"sampled_issue_date":"11/01/1972","magazine_title":"Penthouse","title_code":"PENT"},{"sample_period_ending":"1972-12-31T00:00:00Z","sample_period_start":"1972-07-01T00:00:00Z","state_region":"Massachusetts","state_population":5689170,"sampled_mail_subscriptions":988,"sampled_single_copy_sales":76180,"sampled_total_sales":77168,"sampled_issue_date":"11/01/1972","magazine_title":"Penthouse","title_code":"PENT"},{"sample_period_ending":"1972-12-31T00:00:00Z","sample_period_start":"1972-07-01T00:00:00Z","state_region":"Rhode Island","state_population":946725,"sampled_mail_subscriptions":160,"sampled_single_copy_sales":5980,"sampled_total_sales":6140,"sampled_issue_date":"11/01/1972","magazine_title":"Penthouse","title_code":"PENT"},{"sample_period_ending":"1972-12-31T00:00:00Z","sample_period_start":"1972-07-01T00:00:00Z","state_region":"Connecticut","state_population":3031709,"sampled_mail_subscriptions":641,"sampled_single_copy_sales":41600,"sampled_total_sales":42241,"sampled_issue_date":"11/01/1972","magazine_title":"Penthouse","title_code":"PENT"},{"sample_period_ending":"1972-12-31T00:00:00Z","sample_period_start":"1972-07-01T00:00:00Z","state_region":"New York","state_population":18236967,"sampled_mail_subscriptions":3879,"sampled_single_copy_sales":205819,"sampled_total_sales":209698,"sampled_issue_date":"11/01/1972","magazine_title":"Penthouse","title_code":"PENT"},{"sample_period_ending":"1972-12-31T00:00:00Z","sample_period_start":"1972-07-01T00:00:00Z","state_region":"New Jersey","state_population":7168164,"sampled_mail_subscriptions":1548,"sampled_single_copy_sales":78646,"sampled_total_sales":80194,"sampled_issue_date":"11/01/1972","magazine_title":"Penthouse","title_code":"PENT"},{"sample_period_ending":"1972-12-31T00:00:00Z","sample_period_start":"1972-07-01T00:00:00Z","state_region":"Pennsylvania","state_population":11793909,"sampled_mail_subscriptions":1631,"sampled_single_copy_sales":116116,"sampled_total_sales":117747,"sampled_issue_date":"11/01/1972","magazine_title":"Penthouse","title_code":"PENT"},{"sample_period_ending":"1972-12-31T00:00:00Z","sample_period_start":"1972-07-01T00:00:00Z","state_region":"Ohio","state_population":10652017,"sampled_mail_subscriptions":1761,"sampled_single_copy_sales":94913,"sampled_total_sales":96674,"sampled_issue_date":"11/01/1972","magazine_title":"Penthouse","title_code":"PENT"},{"sample_period_ending":"1972-12-31T00:00:00Z","sample_period_start":"1972-07-01T00:00:00Z","state_region":"Indiana","state_population":5193669,"sampled_mail_subscriptions":912,"sampled_single_copy_sales":56095,"sampled_total_sales":57007,"sampled_issue_date":"11/01/1972","magazine_title":"Penthouse","title_code":"PENT"},{"sample_period_ending":"1972-12-31T00:00:00Z","sample_period_start":"1972-07-01T00:00:00Z","state_region":"Illinois","state_population":11113976,"sampled_mail_subscriptions":2063,"sampled_single_copy_sales":97643,"sampled_total_sales":99706,"sampled_issue_date":"11/01/1972","magazine_title":"Penthouse","title_code":"PENT"},{"sample_period_ending":"1972-12-31T00:00:00Z","sample_period_start":"1972-07-01T00:00:00Z","state_region":"Michigan","state_population":8875083,"sampled_mail_subscriptions":1394,"sampled_single_copy_sales":107249,"sampled_total_sales":108643,"sampled_issue_date":"11/01/1972","magazine_title":"Penthouse","title_code":"PENT"},{"sample_period_ending":"1972-12-31T00:00:00Z","sample_period_start":"1972-07-01T00:00:00Z","state_region":"Wisconsin","state_population":4417731,"sampled_mail_subscriptions":865,"sampled_single_copy_sales":39234,"sampled_total_sales":40099,"sampled_issue_date":"11/01/1972","magazine_title":"Penthouse","title_code":"PENT"},{"sample_period_ending":"1972-12-31T00:00:00Z","sample_period_start":"1972-07-01T00:00:00Z","state_region":"Minnesota","state_population":3804971,"sampled_mail_subscriptions":490,"sampled_single_copy_sales":29510,"sampled_total_sales":30000,"sampled_issue_date":"11/01/1972","magazine_title":"Penthouse","title_code":"PENT"},{"sample_period_ending":"1972-12-31T00:00:00Z","sample_period_start":"1972-07-01T00:00:00Z","state_region":"Iowa","state_population":2824376,"sampled_mail_subscriptions":337,"sampled_single_copy_sales":19234,"sampled_total_sales":19571,"sampled_issue_date":"11/01/1972","magazine_title":"Penthouse","title_code":"PENT"},{"sample_period_ending":"1972-12-31T00:00:00Z","sample_period_start":"1972-07-01T00:00:00Z","state_region":"Missouri","state_population":4676501,"sampled_mail_subscriptions":811,"sampled_single_copy_sales":42874,"sampled_total_sales":43685,"sampled_issue_date":"11/01/1972","magazine_title":"Penthouse","title_code":"PENT"},{"sample_period_ending":"1972-12-31T00:00:00Z","sample_period_start":"1972-07-01T00:00:00Z","state_region":"North Dakota","state_population":617761,"sampled_mail_subscriptions":60,"sampled_single_copy_sales":4238,"sampled_total_sales":4298,"sampled_issue_date":"11/01/1972","magazine_title":"Penthouse","title_code":"PENT"},{"sample_period_ending":"1972-12-31T00:00:00Z","sample_period_start":"1972-07-01T00:00:00Z","state_region":"South Dakota","state_population":665507,"sampled_mail_subscriptions":53,"sampled_single_copy_sales":4290,"sampled_total_sales":4343,"sampled_issue_date":"11/01/1972","magazine_title":"Penthouse","title_code":"PENT"},{"sample_period_ending":"1972-12-31T00:00:00Z","sample_period_start":"1972-07-01T00:00:00Z","state_region":"Nebraska","state_population":1483493,"sampled_mail_subscriptions":276,"sampled_single_copy_sales":11310,"sampled_total_sales":11586,"sampled_issue_date":"11/01/1972","magazine_title":"Penthouse","title_code":"PENT"},{"sample_period_ending":"1972-12-31T00:00:00Z","sample_period_start":"1972-07-01T00:00:00Z","state_region":"Kansas","state_population":2246578,"sampled_mail_subscriptions":498,"sampled_single_copy_sales":19552,"sampled_total_sales":20050,"sampled_issue_date":"11/01/1972","magazine_title":"Penthouse","title_code":"PENT"},{"sample_period_ending":"1972-12-31T00:00:00Z","sample_period_start":"1972-07-01T00:00:00Z","state_region":"Delaware","state_population":548104,"sampled_mail_subscriptions":116,"sampled_single_copy_sales":11700,"sampled_total_sales":11816,"sampled_issue_date":"11/01/1972","magazine_title":"Penthouse","title_code":"PENT"},{"sample_period_ending":"1972-12-31T00:00:00Z","sample_period_start":"1972-07-01T00:00:00Z","state_region":"Maryland","state_population":3922399,"sampled_mail_subscriptions":978,"sampled_single_copy_sales":29250,"sampled_total_sales":30228,"sampled_issue_date":"11/01/1972","magazine_title":"Penthouse","title_code":"PENT"},{"sample_period_ending":"1972-12-31T00:00:00Z","sample_period_start":"1972-07-01T00:00:00Z","state_region":"District of Columbia","state_population":756510,"sampled_mail_subscriptions":280,"sampled_single_copy_sales":71500,"sampled_total_sales":71780,"sampled_issue_date":"11/01/1972","magazine_title":"Penthouse","title_code":"PENT"},{"sample_period_ending":"1972-12-31T00:00:00Z","sample_period_start":"1972-07-01T00:00:00Z","state_region":"Virginia","state_population":4648494,"sampled_mail_subscriptions":1081,"sampled_single_copy_sales":36790,"sampled_total_sales":37871,"sampled_issue_date":"11/01/1972","magazine_title":"Penthouse","title_code":"PENT"},{"sample_period_ending":"1972-12-31T00:00:00Z","sample_period_start":"1972-07-01T00:00:00Z","state_region":"West Virginia","state_population":1744237,"sampled_mail_subscriptions":126,"sampled_single_copy_sales":13519,"sampled_total_sales":13645,"sampled_issue_date":"11/01/1972","magazine_title":"Penthouse","title_code":"PENT"},{"sample_period_ending":"1972-12-31T00:00:00Z","sample_period_start":"1972-07-01T00:00:00Z","state_region":"North Carolina","state_population":5082059,"sampled_mail_subscriptions":697,"sampled_single_copy_sales":41535,"sampled_total_sales":42232,"sampled_issue_date":"11/01/1972","magazine_title":"Penthouse","title_code":"PENT"},{"sample_period_ending":"1972-12-31T00:00:00Z","sample_period_start":"1972-07-01T00:00:00Z","state_region":"South Carolina","state_population":2590516,"sampled_mail_subscriptions":329,"sampled_single_copy_sales":19890,"sampled_total_sales":20219,"sampled_issue_date":"11/01/1972","magazine_title":"Penthouse","title_code":"PENT"},{"sample_period_ending":"1972-12-31T00:00:00Z","sample_period_start":"1972-07-01T00:00:00Z","state_region":"Georgia","state_population":4589575,"sampled_mail_subscriptions":832,"sampled_single_copy_sales":59150,"sampled_total_sales":59982,"sampled_issue_date":"11/01/1972","magazine_title":"Penthouse","title_code":"PENT"},{"sample_period_ending":"1972-12-31T00:00:00Z","sample_period_start":"1972-07-01T00:00:00Z","state_region":"Florida","state_population":6789443,"sampled_mail_subscriptions":1674,"sampled_single_copy_sales":85566,"sampled_total_sales":87240,"sampled_issue_date":"11/01/1972","magazine_title":"Penthouse","title_code":"PENT"},{"sample_period_ending":"1972-12-31T00:00:00Z","sample_period_start":"1972-07-01T00:00:00Z","state_region":"Kentucky","state_population":3218706,"sampled_mail_subscriptions":435,"sampled_single_copy_sales":23244,"sampled_total_sales":23679,"sampled_issue_date":"11/01/1972","magazine_title":"Penthouse","title_code":"PENT"},{"sample_period_ending":"1972-12-31T00:00:00Z","sample_period_start":"1972-07-01T00:00:00Z","state_region":"Tennessee","state_population":3923687,"sampled_mail_subscriptions":396,"sampled_single_copy_sales":27941,"sampled_total_sales":28337,"sampled_issue_date":"11/01/1972","magazine_title":"Penthouse","title_code":"PENT"},{"sample_period_ending":"1972-12-31T00:00:00Z","sample_period_start":"1972-07-01T00:00:00Z","state_region":"Alabama","state_population":3444165,"sampled_mail_subscriptions":355,"sampled_single_copy_sales":20852,"sampled_total_sales":21207,"sampled_issue_date":"11/01/1972","magazine_title":"Penthouse","title_code":"PENT"},{"sample_period_ending":"1972-12-31T00:00:00Z","sample_period_start":"1972-07-01T00:00:00Z","state_region":"Mississippi","state_population":2216912,"sampled_mail_subscriptions":183,"sampled_single_copy_sales":10114,"sampled_total_sales":10297,"sampled_issue_date":"11/01/1972","magazine_title":"Penthouse","title_code":"PENT"},{"sample_period_ending":"1972-12-31T00:00:00Z","sample_period_start":"1972-07-01T00:00:00Z","state_region":"Arkansas","state_population":1923295,"sampled_mail_subscriptions":174,"sampled_single_copy_sales":12818,"sampled_total_sales":12992,"sampled_issue_date":"11/01/1972","magazine_title":"Penthouse","title_code":"PENT"},{"sample_period_ending":"1972-12-31T00:00:00Z","sample_period_start":"1972-07-01T00:00:00Z","state_region":"Louisiana","state_population":3641306,"sampled_mail_subscriptions":373,"sampled_single_copy_sales":25402,"sampled_total_sales":25775,"sampled_issue_date":"11/01/1972","magazine_title":"Penthouse","title_code":"PENT"},{"sample_period_ending":"1972-12-31T00:00:00Z","sample_period_start":"1972-07-01T00:00:00Z","state_region":"Oklahoma","state_population":2559229,"sampled_mail_subscriptions":333,"sampled_single_copy_sales":28730,"sampled_total_sales":29063,"sampled_issue_date":"11/01/1972","magazine_title":"Penthouse","title_code":"PENT"},{"sample_period_ending":"1972-12-31T00:00:00Z","sample_period_start":"1972-07-01T00:00:00Z","state_region":"Texas","state_population":11196730,"sampled_mail_subscriptions":1676,"sampled_single_copy_sales":106536,"sampled_total_sales":108212,"sampled_issue_date":"11/01/1972","magazine_title":"Penthouse","title_code":"PENT"},{"sample_period_ending":"1972-12-31T00:00:00Z","sample_period_start":"1972-07-01T00:00:00Z","state_region":"Montana","state_population":694409,"sampled_mail_subscriptions":71,"sampled_single_copy_sales":5434,"sampled_total_sales":5505,"sampled_issue_date":"11/01/1972","magazine_title":"Penthouse","title_code":"PENT"},{"sample_period_ending":"1972-12-31T00:00:00Z","sample_period_start":"1972-07-01T00:00:00Z","state_region":"Idaho","state_population":712567,"sampled_mail_subscriptions":93,"sampled_single_copy_sales":6500,"sampled_total_sales":6593,"sampled_issue_date":"11/01/1972","magazine_title":"Penthouse","title_code":"PENT"},{"sample_period_ending":"1972-12-31T00:00:00Z","sample_period_start":"1972-07-01T00:00:00Z","state_region":"Wyoming","state_population":332416,"sampled_mail_subscriptions":53,"sampled_single_copy_sales":2340,"sampled_total_sales":2393,"sampled_issue_date":"11/01/1972","magazine_title":"Penthouse","title_code":"PENT"},{"sample_period_ending":"1972-12-31T00:00:00Z","sample_period_start":"1972-07-01T00:00:00Z","state_region":"Colorado","state_population":2207259,"sampled_mail_subscriptions":481,"sampled_single_copy_sales":33592,"sampled_total_sales":34073,"sampled_issue_date":"11/01/1972","magazine_title":"Penthouse","title_code":"PENT"},{"sample_period_ending":"1972-12-31T00:00:00Z","sample_period_start":"1972-07-01T00:00:00Z","state_region":"New Mexico","state_population":1016000,"sampled_mail_subscriptions":135,"sampled_single_copy_sales":6810,"sampled_total_sales":6945,"sampled_issue_date":"11/01/1972","magazine_title":"Penthouse","title_code":"PENT"},{"sample_period_ending":"1972-12-31T00:00:00Z","sample_period_start":"1972-07-01T00:00:00Z","state_region":"Arizona","state_population":1770900,"sampled_mail_subscriptions":332,"sampled_single_copy_sales":22620,"sampled_total_sales":22952,"sampled_issue_date":"11/01/1972","magazine_title":"Penthouse","title_code":"PENT"},{"sample_period_ending":"1972-12-31T00:00:00Z","sample_period_start":"1972-07-01T00:00:00Z","state_region":"Utah","state_population":1059273,"sampled_mail_subscriptions":109,"sampled_single_copy_sales":13390,"sampled_total_sales":13499,"sampled_issue_date":"11/01/1972","magazine_title":"Penthouse","title_code":"PENT"},{"sample_period_ending":"1972-12-31T00:00:00Z","sample_period_start":"1972-07-01T00:00:00Z","state_region":"Nevada","state_population":488738,"sampled_mail_subscriptions":132,"sampled_single_copy_sales":11700,"sampled_total_sales":11832,"sampled_issue_date":"11/01/1972","magazine_title":"Penthouse","title_code":"PENT"},{"sample_period_ending":"1972-12-31T00:00:00Z","sample_period_start":"1972-07-01T00:00:00Z","state_region":"Alaska","state_population":300382,"sampled_mail_subscriptions":116,"sampled_single_copy_sales":5538,"sampled_total_sales":5654,"sampled_issue_date":"11/01/1972","magazine_title":"Penthouse","title_code":"PENT"},{"sample_period_ending":"1972-12-31T00:00:00Z","sample_period_start":"1972-07-01T00:00:00Z","state_region":"Washington","state_population":3409169,"sampled_mail_subscriptions":552,"sampled_single_copy_sales":38350,"sampled_total_sales":38902,"sampled_issue_date":"11/01/1972","magazine_title":"Penthouse","title_code":"PENT"},{"sample_period_ending":"1972-12-31T00:00:00Z","sample_period_start":"1972-07-01T00:00:00Z","state_region":"Oregon","state_population":2091385,"sampled_mail_subscriptions":310,"sampled_single_copy_sales":21180,"sampled_total_sales":21490,"sampled_issue_date":"11/01/1972","magazine_title":"Penthouse","title_code":"PENT"},{"sample_period_ending":"1972-12-31T00:00:00Z","sample_period_start":"1972-07-01T00:00:00Z","state_region":"California","state_population":19953134,"sampled_mail_subscriptions":4319,"sampled_single_copy_sales":251161,"sampled_total_sales":255480,"sampled_issue_date":"11/01/1972","magazine_title":"Penthouse","title_code":"PENT"},{"sample_period_ending":"1972-12-31T00:00:00Z","sample_period_start":"1972-07-01T00:00:00Z","state_region":"Hawaii","state_population":768561,"sampled_mail_subscriptions":183,"sampled_single_copy_sales":11700,"sampled_total_sales":11883,"sampled_issue_date":"11/01/1972","magazine_title":"Penthouse","title_code":"PENT"},{"sample_period_ending":"1972-12-31T00:00:00Z","sample_period_start":"1972-07-01T00:00:00Z","state_region":"Miscellaneous","sampled_mail_subscriptions":0,"sampled_single_copy_sales":0,"sampled_total_sales":0,"sampled_issue_date":"11/01/1972","magazine_title":"Penthouse","title_code":"PENT"},{"sample_period_ending":"1972-12-31T00:00:00Z","sample_period_start":"1972-07-01T00:00:00Z","state_region":"Unclassified","sampled_mail_subscriptions":0,"sampled_single_copy_sales":0,"sampled_total_sales":0,"sampled_issue_date":"11/01/1972","magazine_title":"Penthouse","title_code":"PENT"},{"sample_period_ending":"1972-12-31T00:00:00Z","sample_period_start":"1972-07-01T00:00:00Z","state_region":"Possessions & Other Areas","sampled_mail_subscriptions":106,"sampled_single_copy_sales":2860,"sampled_total_sales":2966,"sampled_issue_date":"11/01/1972","magazine_title":"Penthouse","title_code":"PENT"},{"sample_period_ending":"1972-12-31T00:00:00Z","sample_period_start":"1972-07-01T00:00:00Z","state_region":"U.S. & Possessions, etc.","sampled_mail_subscriptions":35714,"sampled_single_copy_sales":2132505,"sampled_total_sales":2168219,"sampled_issue_date":"11/01/1972","magazine_title":"Penthouse","title_code":"PENT"},{"sample_period_ending":"1972-12-31T00:00:00Z","sample_period_start":"1972-07-01T00:00:00Z","state_region":"Canada","sampled_mail_subscriptions":1466,"sampled_single_copy_sales":159685,"sampled_total_sales":161151,"sampled_issue_date":"11/01/1972","magazine_title":"Penthouse","title_code":"PENT"},{"sample_period_ending":"1972-12-31T00:00:00Z","sample_period_start":"1972-07-01T00:00:00Z","state_region":"Foreign","sampled_mail_subscriptions":110,"sampled_single_copy_sales":0,"sampled_total_sales":110,"sampled_issue_date":"11/01/1972","magazine_title":"Penthouse","title_code":"PENT"},{"sample_period_ending":"1972-12-31T00:00:00Z","sample_period_start":"1972-07-01T00:00:00Z","state_region":"Unclassified","sampled_mail_subscriptions":0,"sampled_single_copy_sales":0,"sampled_total_sales":0,"sampled_issue_date":"11/01/1972","magazine_title":"Penthouse","title_code":"PENT"},{"sample_period_ending":"1972-12-31T00:00:00Z","sample_period_start":"1972-07-01T00:00:00Z","state_region":"Military or Civilian Personnel Overseas","sampled_mail_subscriptions":2454,"sampled_single_copy_sales":58002,"sampled_total_sales":60456,"sampled_issue_date":"11/01/1972","magazine_title":"Penthouse","title_code":"PENT"},{"sample_period_ending":"1972-12-31T00:00:00Z","sample_period_start":"1972-07-01T00:00:00Z","state_region":"ALL","sampled_mail_subscriptions":39744,"sampled_single_copy_sales":2350192,"sampled_total_sales":2389936,"sampled_issue_date":"11/01/1972","magazine_title":"Penthouse","title_code":"PENT"}]